Workbook

Sheet Dashboard
A1: CONTROL UV DTF — RENDIMIENTO DEL ROLLO A
A3: Indicador principal | B3: Valor
A4: Rollo A actualmente en uso | B4: ='Control de rollos'!B2 -> A-001
A5: Fecha de inicio | B5: ='Control de rollos'!C2 -> 46272
A6: Metros iniciales | B6: ='Control de rollos'!E2 -> 100
A7: Metros impresos | B7: ='Control de rollos'!F2 -> 36.117
A8: Metros restantes | B8: ='Control de rollos'!G2 -> 63.883
A9: Trabajos registrados | B9: ='Control de rollos'!K2 -> 61
A10: Total cobrado por ese rollo A | B10: =SUM('Registro de trabajos'!H:H) -> 2777.2
A11: Ingreso promedio por metro impreso | B11: =IFERROR(B10/(SUM('Registro de trabajos'!E:E)+SUM('Registro de trabajos'!G:G)),0) -> 38.512314
A12: Nota: | B12: El cobro corresponde al trabajo completo A+B y se suma una sola vez.
A14: HISTORIAL DE ROLLOS A Y B
A15: Tipo | B15: ID del rollo | C15: Fecha inicio | D15: Fecha término | E15: Metros iniciales | F15: Metros impresos | G15: Metros restantes | H15: Trabajos | I15: Estado | J15: Total cobrado
A16: ='Control de rollos'!A2 -> A | B16: ='Control de rollos'!B2 -> A-001 | C16: ='Control de rollos'!C2 -> 46272 | D16: =IF('Control de rollos'!D2="","",'Control de rollos'!D2) | E16: ='Control de rollos'!E2 -> 100 | F16: =SUMIF('Registro de trabajos'!D:D,B16,'Registro de trabajos'!E:E) -> 36.117 | G16: =MAX(0,E16-F16) -> 63.883 | H16: =COUNTIF('Registro de trabajos'!D:D,B16) -> 61 | I16: ='Control de rollos'!M2 -> EN USO | J16: =IF('Control de rollos'!B2="","",'Control de rollos'!H2) -> 2777.2
A17: ='Control de rollos'!A3 -> B | B17: ='Control de rollos'!B3 -> B-001 | C17: ='Control de rollos'!C3 -> 46241 | D17: ='Control de rollos'!D3 -> 46273 | E17: ='Control de rollos'!E3 -> 100 | F17: =SUMIF('Registro de trabajos'!F:F,B17,'Registro de trabajos'!G:G) -> 5.115 | G17: =MAX(0,E17-F17) -> 94.885 | H17: =COUNTIF('Registro de trabajos'!F:F,B17) -> 6 | I17: ='Control de rollos'!M3 -> FINALIZADO | J17: =IF('Control de rollos'!B3="","",'Control de rollos'!H3) -> 0
A18: ='Control de rollos'!A4 -> B | B18: ='Control de rollos'!B4 -> B-002 | C18: ='Control de rollos'!C4 -> 46273 | D18: =IF('Control de rollos'!D4="","",'Control de rollos'!D4) | E18: ='Control de rollos'!E4 -> 100 | F18: =SUMIF('Registro de trabajos'!F:F,B18,'Registro de trabajos'!G:G) -> 30.88 | G18: =MAX(0,E18-F18) -> 69.12 | H18: =COUNTIF('Registro de trabajos'!F:F,B18) -> 55 | I18: ='Control de rollos'!M4 -> EN USO | J18: =IF('Control de rollos'!B4="","",'Control de rollos'!H4) -> 0

Sheet Registro de trabajos
A1: REGISTRO DE TRABAJOS UV DTF
A2: Una fila = un trabajo. Registra los metros A y B, pero el cobro se coloca UNA SOLA VEZ porque corresponde al trabajo completo A+B.
A3: Fecha | B3: N° de trabajo | C3: Cliente / Descripción | D3: Rollo A | E3: Metros impresos (m) | F3: Rollo B | G3: Metros B (m) | H3: Cobrado (A+B) | I3: Medio de pago | J3: Observaciones
A4: 46273 | B4: 1 | C4: 951 112 094 | D4: A-001 | E4: 1.5 | F4: B-001 | G4: 1.5 | H4: 95 | I4: Yapeo | J4: PLANCHA Y MEDIA
A5: 46272 | B5: 2 | C5: 949 337 517 | D5: A-001 | E5: 1.8 | F5: B-001 | G5: 1.8 | H5: 108 | I5: Yapeo | J5: 1 METRO + 80 CM
A6: 46272 | B6: 3 | C6: STEWART | D6: A-001 | E6: 0.105 | F6: B-001 | G6: 0.105 | H6: 15 | I6: Yapeo | J6: A4
A7: 46273 | B7: 4 | C7: edymil | D7: A-001 | E7: 0.21 | F7: B-002 | G7: 0.21 | H7: 25 | I7: Yapeo | J7: A3
A8: 46273 | B8: 5 | C8: JUAN VERGARA | D8: A-001 | E8: 0.5 | F8: B-001 | G8: 0.5 | H8: 40 | I8: Yapeo | J8: 1/2 Plancha
A9: 46273 | B9: 6 | C9: MIGUEL | D9: A-001 | E9: 1 | F9: B-001 | G9: 1 | H9: 70 | I9: Yapeo | J9: 1 PLANCHA
A10: 46273 | B10: 7 | C10: JACK PRINT | D10: A-001 | E10: 1 | F10: B-002 | G10: 1 | H10: 60 | I10: Yapeo | J10: 1 PLANCHA
A11: 46273 | B11: 8 | C11: gigantografias uv | D11: A-001 | E11: 1 | F11: B-002 | G11: 1 | H11: 60 | I11: Yapeo | J11: 1 PLANCHA
A12: 46274 | B12: 9 | C12: FUTURO | D12: A-001 | E12: 0.3 | F12: B-002 | G12: 0.3 | H12: 30 | I12: Yapeo | J12: A3+
A13: 46274 | B13: 10 | C13: SUPER ART ESTUDIO | D13: A-001 | E13: 0.21 | F13: B-002 | G13: 0.21 | H13: 25 | I13: Yapeo | J13: A3
A14: 46274 | B14: 11 | C14: DINCA | D14: A-001 | E14: 0.8 | F14: B-002 | G14: 0.8 | H14: 50 | I14: Yapeo | J14: 1/2 plancha +
A15: 46274 | B15: 12 | C15: MAYOGA | D15: A-001 | E15: 1 | F15: B-002 | G15: 1 | H15: 60 | I15: Yapeo | J15: 1 PLANCHA
... A51: 46282 | B51: 45 | C51: TALENTUS | D51: A-001 | E51: 0.5 | F51: B-002 | G51: 0.5 | H51: 40 | I51: Yapeo | J51: 1/2 PLANCHA
A52: 46282 | B52: 46 | C52: CARLOS | D52: A-001 | E52: 0.11 | F52: B-002 | G52: 0.11 | I52: Yapeo | J52: A4
A53: 46282 | B53: 47 | C53: FREPAP | D53: A-001 | E53: 2.5 | F53: B-002 | G53: 2.5 | H53: 180 | I53: Yapeo | J53: 2 PLANCHAS Y MEDIA
A54: 46282 | B54: 48 | C54: AUTONORT | D54: A-001 | E54: 0.1 | F54: B-002 | G54: 0.1 | H54: 10 | I54: Yapeo | J54: A4+
A55: 46282 | B55: 49 | C55: MAYOGA | D55: A-001 | E55: 0.15 | F55: B-002 | G55: 0.11 | H55: 15 | I55: Yapeo | J55: A4
A56: 46282 | B56: 50 | C56: MAYOGA | D56: A-001 | E56: 0.15 | F56: B-002 | G56: 0.11 | H56: 15 | I56: Yapeo | J56: A4
A57: 46283 | B57: 51 | C57: GRAFICA FUTURO | D57: A-001 | E57: 0.11 | F57: B-002 | G57: 0.11 | H57: 15 | I57: Yapeo | J57: A4
A58: 46283 | B58: 52 | C58: MUG | D58: A-001 | E58: 0.11 | F58: B-002 | G58: 0.11 | H58: 39 | I58: Yapeo | J58: A4
A59: 46283 | B59: 53 | C59: FUSION CLIENTES | D59: A-001 | E59: 0.11 | F59: B-002 | G59: 0.11 | H59: 25 | I59: Yapeo | J59: A4
A60: 46283 | B60: 54 | C60: CLIENTE | D60: A-001 | E60: 0.11 | F60: B-002 | G60: 0.11 | H60: 15 | I60: Yapeo | J60: A4
A61: 46283 | B61: 55 | C61: BARRO | D61: A-001 | E61: 0.11 | F61: B-002 | G61: 0.11 | H61: 20 | I61: Yapeo | J61: A4
A62: 46283 | B62: 56 | C62: JUNIOR CODEX | D62: A-001 | E62: 0.5 | F62: B-002 | G62: 0.5 | H62: 40 | I62: Efectivo | J62: 1/2 PLANCHA
A63: 46283 | B63: 57 | C63: MAYOGA | D63: A-001 | E63: 0.11 | F63: B-002 | G63: 0.11 | H63: 15 | I63: Yapeo | J63: A4
A64: 46283 | B64: 58 | C64: AUTONORT CLIENTE 2 | D64: A-001 | E64: 0.11 | F64: B-002 | G64: 0.11 | H64: 20 | I64: Efectivo | J64: A4

Sheet Control de rollos
A1: Tipo | B1: ID del rollo | C1: Fecha inicio | D1: Fecha término | E1: Metros iniciales | F1: Metros impresos | G1: Metros restantes | H1: Total cobrado | I1: Costo | J1: Ganancia estimada | K1: Trabajos | L1: Metros B usados | M1: Estado
A2: A | B2: =IF(A2="","",A2&"-"&TEXT(COUNTIF($A$2:A2,A2),"000")) -> A-001 | C2: 46272 | E2: =Configuración!B3 -> 100 | F2: =SUMIF('Registro de trabajos'!D:D,B2,'Registro de trabajos'!E:E) -> 36.117 | G2: =MAX(0,E2-F2) -> 63.883 | H2: =SUMIF('Registro de trabajos'!D:D,B2,'Registro de trabajos'!H:H) -> 2777.2 | I2: =Configuración!B4 -> 0 | J2: =H2-I2 -> 2777.2 | K2: =COUNTIF('Registro de trabajos'!D:D,B2) -> 61 | L2: =SUMIF('Registro de trabajos'!D:D,B2,'Registro de trabajos'!G:G) -> 35.995 | M2: EN USO
A3: B | B3: =IF(A3="","",A3&"-"&TEXT(COUNTIF($A$2:A3,A3),"000")) -> B-001 | C3: 46241 | D3: 46273 | E3: 100 | F3: =SUMIF('Registro de trabajos'!F:F,B3,'Registro de trabajos'!G:G) -> 5.115 | G3: =MAX(0,E3-F3) -> 94.885 | H3: 0 | I3: 0 | J3: 0 | K3: =COUNTIF('Registro de trabajos'!F:F,B3) -> 6 | L3: =F3 -> 5.115 | M3: FINALIZADO
A4: B | B4: =IF(A4="","",A4&"-"&TEXT(COUNTIF($A$2:A4,A4),"000")) -> B-002 | C4: 46273 | E4: =Configuración!B3 -> 100 | F4: =SUMIF('Registro de trabajos'!F:F,B4,'Registro de trabajos'!G:G) -> 30.88 | G4: =MAX(0,E4-F4) -> 69.12 | H4: 0 | I4: 0 | J4: 0 | K4: =COUNTIF('Registro de trabajos'!F:F,B4) -> 55 | L4: =F4 -> 30.88 | M4: EN USO
A5: =IF('Control de rollos'!D2<>"","A","") | B5: =IF(A5="","",A5&"-"&TEXT(COUNTIF($A$2:A5,A5),"000")) | C5: =IF(A5="","",D2) | E5: =IF(A5="","",Configuración!B3) | F5: =IF(A5="","",SUMIF('Registro de trabajos'!D:D,B5,'Registro de trabajos'!E:E)) | G5: =IF(A5="","",MAX(0,E5-F5)) | H5: =IF(A5="","",SUMIF('Registro de trabajos'!D:D,B5,'Registro de trabajos'!H:H)) | I5: =IF(A5="","",Configuración!B4) | J5: =IF(A5="","",H5-I5) | K5: =IF(A5="","",COUNTIF('Registro de trabajos'!D:D,B5)) | L5: =IF(A5="","",SUMIF('Registro de trabajos'!D:D,B5,'Registro de trabajos'!G:G)) | M5: =IF(A5="","",IF(D5="","EN USO","FINALIZADO"))
A6: =IF('Control de rollos'!D4<>"","B","") | B6: =IF(A6="","",A6&"-"&TEXT(COUNTIF($A$2:A6,A6),"000")) | C6: =IF(A6="","",D4) | E6: =IF(A6="","",Configuración!B3) | F6: =IF(A6="","",SUMIF('Registro de trabajos'!F:F,B6,'Registro de trabajos'!G:G)) | G6: =IF(A6="","",MAX(0,E6-F6)) | H6: =IF(A6="","",0) | I6: =IF(A6="","",0) | J6: =IF(A6="","",H6-I6) | K6: =IF(A6="","",COUNTIF('Registro de trabajos'!F:F,B6)) | L6: =IF(A6="","",F6) | M6: =IF(A6="","",IF(D6="","EN USO","FINALIZADO"))
A7: =IF('Control de rollos'!D4<>"","A","") | B7: =IF(A7="","",A7&"-"&TEXT(COUNTIF($A$2:A7,A7),"000")) | C7: =IF(A7="","",D4) | E7: =IF(A7="","",Configuración!B3) | F7: =IF(A7="","",SUMIF('Registro de trabajos'!D:D,B7,'Registro de trabajos'!E:E)) | G7: =IF(A7="","",MAX(0,E7-F7)) | H7: =IF(A7="","",SUMIF('Registro de trabajos'!D:D,B7,'Registro de trabajos'!H:H)) | I7: =IF(A7="","",Configuración!B4) | J7: =IF(A7="","",H7-I7) | K7: =IF(A7="","",COUNTIF('Registro de trabajos'!D:D,B7)) | L7: =IF(A7="","",SUMIF('Registro de trabajos'!D:D,B7,'Registro de trabajos'!G:G)) | M7: =IF(A7="","",IF(D7="","EN USO","FINALIZADO"))
A8: =IF('Control de rollos'!D6<>"","B","") | B8: =IF(A8="","",A8&"-"&TEXT(COUNTIF($A$2:A8,A8),"000")) | C8: =IF(A8="","",D6) | E8: =IF(A8="","",Configuración!B3) | F8: =IF(A8="","",SUMIF('Registro de trabajos'!F:F,B8,'Registro de trabajos'!G:G)) | G8: =IF(A8="","",MAX(0,E8-F8)) | H8: =IF(A8="","",0) | I8: =IF(A8="","",0) | J8: =IF(A8="","",H8-I8) | K8: =IF(A8="","",COUNTIF('Registro de trabajos'!F:F,B8)) | L8: =IF(A8="","",F8) | M8: =IF(A8="","",IF(D8="","EN USO","FINALIZADO"))
A9: =IF('Control de rollos'!D6<>"","A","") | B9: =IF(A9="","",A9&"-"&TEXT(COUNTIF($A$2:A9,A9),"000")) | C9: =IF(A9="","",D6) | E9: =IF(A9="","",Configuración!B3) | F9: =IF(A9="","",SUMIF('Registro de trabajos'!D:D,B9,'Registro de trabajos'!E:E)) | G9: =IF(A9="","",MAX(0,E9-F9)) | H9: =IF(A9="","",SUMIF('Registro de trabajos'!D:D,B9,'Registro de trabajos'!H:H)) | I9: =IF(A9="","",Configuración!B4) | J9: =IF(A9="","",H9-I9) | K9: =IF(A9="","",COUNTIF('Registro de trabajos'!D:D,B9)) | L9: =IF(A9="","",SUMIF('Registro de trabajos'!D:D,B9,'Registro de trabajos'!G:G)) | M9: =IF(A9="","",IF(D9="","EN USO","FINALIZADO"))
A10: =IF('Control de rollos'!D8<>"","B","") | B10: =IF(A10="","",A10&"-"&TEXT(COUNTIF($A$2:A10,A10),"000")) | C10: =IF(A10="","",D8) | E10: =IF(A10="","",Configuración!B3) | F10: =IF(A10="","",SUMIF('Registro de trabajos'!F:F,B10,'Registro de trabajos'!G:G)) | G10: =IF(A10="","",MAX(0,E10-F10)) | H10: =IF(A10="","",0) | I10: =IF(A10="","",0) | J10: =IF(A10="","",H10-I10) | K10: =IF(A10="","",COUNTIF('Registro de trabajos'!F:F,B10)) | L10: =IF(A10="","",F10) | M10: =IF(A10="","",IF(D10="","EN USO","FINALIZADO"))
A11: =IF('Control de rollos'!D8<>"","A","") | B11: =IF(A11="","",A11&"-"&TEXT(COUNTIF($A$2:A11,A11),"000")) | C11: =IF(A11="","",D8) | E11: =IF(A11="","",Configuración!B3) | F11: =IF(A11="","",SUMIF('Registro de trabajos'!D:D,B11,'Registro de trabajos'!E:E)) | G11: =IF(A11="","",MAX(0,E11-F11)) | H11: =IF(A11="","",SUMIF('Registro de trabajos'!D:D,B11,'Registro de trabajos'!H:H)) | I11: =IF(A11="","",Configuración!B4) | J11: =IF(A11="","",H11-I11) | K11: =IF(A11="","",COUNTIF('Registro de trabajos'!D:D,B11)) | L11: =IF(A11="","",SUMIF('Registro de trabajos'!D:D,B11,'Registro de trabajos'!G:G)) | M11: =IF(A11="","",IF(D11="","EN USO","FINALIZADO"))
A12: =IF('Control de rollos'!D10<>"","B","") | B12: =IF(A12="","",A12&"-"&TEXT(COUNTIF($A$2:A12,A12),"000")) | C12: =IF(A12="","",D10) | E12: =IF(A12="","",Configuración!B3) | F12: =IF(A12="","",SUMIF('Registro de trabajos'!F:F,B12,'Registro de trabajos'!G:G)) | G12: =IF(A12="","",MAX(0,E12-F12)) | H12: =IF(A12="","",0) | I12: =IF(A12="","",0) | J12: =IF(A12="","",H12-I12) | K12: =IF(A12="","",COUNTIF('Registro de trabajos'!F:F,B12)) | L12: =IF(A12="","",F12) | M12: =IF(A12="","",IF(D12="","EN USO","FINALIZADO"))
A13: =IF('Control de rollos'!D10<>"","A","") | B13: =IF(A13="","",A13&"-"&TEXT(COUNTIF($A$2:A13,A13),"000")) | C13: =IF(A13="","",D10) | E13: =IF(A13="","",Configuración!B3) | F13: =IF(A13="","",SUMIF('Registro de trabajos'!D:D,B13,'Registro de trabajos'!E:E)) | G13: =IF(A13="","",MAX(0,E13-F13)) | H13: =IF(A13="","",SUMIF('Registro de trabajos'!D:D,B13,'Registro de trabajos'!H:H)) | I13: =IF(A13="","",Configuración!B4) | J13: =IF(A13="","",H13-I13) | K13: =IF(A13="","",COUNTIF('Registro de trabajos'!D:D,B13)) | L13: =IF(A13="","",SUMIF('Registro de trabajos'!D:D,B13,'Registro de trabajos'!G:G)) | M13: =IF(A13="","",IF(D13="","EN USO","FINALIZADO"))
A14: =IF('Control de rollos'!D12<>"","B","") | B14: =IF(A14="","",A14&"-"&TEXT(COUNTIF($A$2:A14,A14),"000")) | C14: =IF(A14="","",D12) | E14: =IF(A14="","",Configuración!B3) | F14: =IF(A14="","",SUMIF('Registro de trabajos'!F:F,B14,'Registro de trabajos'!G:G)) | G14: =IF(A14="","",MAX(0,E14-F14)) | H14: =IF(A14="","",0) | I14: =IF(A14="","",0) | J14: =IF(A14="","",H14-I14) | K14: =IF(A14="","",COUNTIF('Registro de trabajos'!F:F,B14)) | L14: =IF(A14="","",F14) | M14: =IF(A14="","",IF(D14="","EN USO","FINALIZADO"))
A15: =IF('Control de rollos'!D12<>"","A","") | B15: =IF(A15="","",A15&"-"&TEXT(COUNTIF($A$2:A15,A15),"000")) | C15: =IF(A15="","",D12) | E15: =IF(A15="","",Configuración!B3) | F15: =IF(A15="","",SUMIF('Registro de trabajos'!D:D,B15,'Registro de trabajos'!E:E)) | G15: =IF(A15="","",MAX(0,E15-F15)) | H15: =IF(A15="","",SUMIF('Registro de trabajos'!D:D,B15,'Registro de trabajos'!H:H)) | I15: =IF(A15="","",Configuración!B4) | J15: =IF(A15="","",H15-I15) | K15: =IF(A15="","",COUNTIF('Registro de trabajos'!D:D,B15)) | L15: =IF(A15="","",SUMIF('Registro de trabajos'!D:D,B15,'Registro de trabajos'!G:G)) | M15: =IF(A15="","",IF(D15="","EN USO","FINALIZADO"))
A16: =IF('Control de rollos'!D14<>"","B","") | B16: =IF(A16="","",A16&"-"&TEXT(COUNTIF($A$2:A16,A16),"000")) | C16: =IF(A16="","",D14) | E16: =IF(A16="","",Configuración!B3) | F16: =IF(A16="","",SUMIF('Registro de trabajos'!F:F,B16,'Registro de trabajos'!G:G)) | G16: =IF(A16="","",MAX(0,E16-F16)) | H16: =IF(A16="","",0) | I16: =IF(A16="","",0) | J16: =IF(A16="","",H16-I16) | K16: =IF(A16="","",COUNTIF('Registro de trabajos'!F:F,B16)) | L16: =IF(A16="","",F16) | M16: =IF(A16="","",IF(D16="","EN USO","FINALIZADO"))
A17: =IF('Control de rollos'!D14<>"","A","") | B17: =IF(A17="","",A17&"-"&TEXT(COUNTIF($A$2:A17,A17),"000")) | C17: =IF(A17="","",D14) | E17: =IF(A17="","",Configuración!B3) | F17: =IF(A17="","",SUMIF('Registro de trabajos'!D:D,B17,'Registro de trabajos'!E:E)) | G17: =IF(A17="","",MAX(0,E17-F17)) | H17: =IF(A17="","",SUMIF('Registro de trabajos'!D:D,B17,'Registro de trabajos'!H:H)) | I17: =IF(A17="","",Configuración!B4) | J17: =IF(A17="","",H17-I17) | K17: =IF(A17="","",COUNTIF('Registro de trabajos'!D:D,B17)) | L17: =IF(A17="","",SUMIF('Registro de trabajos'!D:D,B17,'Registro de trabajos'!G:G)) | M17: =IF(A17="","",IF(D17="","EN USO","FINALIZADO"))
A18: =IF('Control de rollos'!D16<>"","B","") | B18: =IF(A18="","",A18&"-"&TEXT(COUNTIF($A$2:A18,A18),"000")) | C18: =IF(A18="","",D16) | E18: =IF(A18="","",Configuración!B3) | F18: =IF(A18="","",SUMIF('Registro de trabajos'!F:F,B18,'Registro de trabajos'!G:G)) | G18: =IF(A18="","",MAX(0,E18-F18)) | H18: =IF(A18="","",0) | I18: =IF(A18="","",0) | J18: =IF(A18="","",H18-I18) | K18: =IF(A18="","",COUNTIF('Registro de trabajos'!F:F,B18)) | L18: =IF(A18="","",F18) | M18: =IF(A18="","",IF(D18="","EN USO","FINALIZADO"))
A19: =IF('Control de rollos'!D16<>"","A","") | B19: =IF(A19="","",A19&"-"&TEXT(COUNTIF($A$2:A19,A19),"000")) | C19: =IF(A19="","",D16) | E19: =IF(A19="","",Configuración!B3) | F19: =IF(A19="","",SUMIF('Registro de trabajos'!D:D,B19,'Registro de trabajos'!E:E)) | G19: =IF(A19="","",MAX(0,E19-F19)) | H19: =IF(A19="","",SUMIF('Registro de trabajos'!D:D,B19,'Registro de trabajos'!H:H)) | I19: =IF(A19="","",Configuración!B4) | J19: =IF(A19="","",H19-I19) | K19: =IF(A19="","",COUNTIF('Registro de trabajos'!D:D,B19)) | L19: =IF(A19="","",SUMIF('Registro de trabajos'!D:D,B19,'Registro de trabajos'!G:G)) | M19: =IF(A19="","",IF(D19="","EN USO","FINALIZADO"))
A20: =IF('Control de rollos'!D18<>"","B","") | B20: =IF(A20="","",A20&"-"&TEXT(COUNTIF($A$2:A20,A20),"000")) | C20: =IF(A20="","",D18) | E20: =IF(A20="","",Configuración!B3) | F20: =IF(A20="","",SUMIF('Registro de trabajos'!F:F,B20,'Registro de trabajos'!G:G)) | G20: =IF(A20="","",MAX(0,E20-F20)) | H20: =IF(A20="","",0) | I20: =IF(A20="","",0) | J20: =IF(A20="","",H20-I20) | K20: =IF(A20="","",COUNTIF('Registro de trabajos'!F:F,B20)) | L20: =IF(A20="","",F20) | M20: =IF(A20="","",IF(D20="","EN USO","FINALIZADO"))
A21: =IF('Control de rollos'!D18<>"","A","") | B21: =IF(A21="","",A21&"-"&TEXT(COUNTIF($A$2:A21,A21),"000")) | C21: =IF(A21="","",D18) | E21: =IF(A21="","",Configuración!B3) | F21: =IF(A21="","",SUMIF('Registro de trabajos'!D:D,B21,'Registro de trabajos'!E:E)) | G21: =IF(A21="","",MAX(0,E21-F21)) | H21: =IF(A21="","",SUMIF('Registro de trabajos'!D:D,B21,'Registro de trabajos'!H:H)) | I21: =IF(A21="","",Configuración!B4) | J21: =IF(A21="","",H21-I21) | K21: =IF(A21="","",COUNTIF('Registro de trabajos'!D:D,B21)) | L21: =IF(A21="","",SUMIF('Registro de trabajos'!D:D,B21,'Registro de trabajos'!G:G)) | M21: =IF(A21="","",IF(D21="","EN USO","FINALIZADO"))
A22: =IF('Control de rollos'!D20<>"","B","") | B22: =IF(A22="","",A22&"-"&TEXT(COUNTIF($A$2:A22,A22),"000")) | C22: =IF(A22="","",D20) | E22: =IF(A22="","",Configuración!B3) | F22: =IF(A22="","",SUMIF('Registro de trabajos'!F:F,B22,'Registro de trabajos'!G:G)) | G22: =IF(A22="","",MAX(0,E22-F22)) | H22: =IF(A22="","",0) | I22: =IF(A22="","",0) | J22: =IF(A22="","",H22-I22) | K22: =IF(A22="","",COUNTIF('Registro de trabajos'!F:F,B22)) | L22: =IF(A22="","",F22) | M22: =IF(A22="","",IF(D22="","EN USO","FINALIZADO"))
A23: =IF('Control de rollos'!D20<>"","A","") | B23: =IF(A23="","",A23&"-"&TEXT(COUNTIF($A$2:A23,A23),"000")) | C23: =IF(A23="","",D20) | E23: =IF(A23="","",Configuración!B3) | F23: =IF(A23="","",SUMIF('Registro de trabajos'!D:D,B23,'Registro de trabajos'!E:E)) | G23: =IF(A23="","",MAX(0,E23-F23)) | H23: =IF(A23="","",SUMIF('Registro de trabajos'!D:D,B23,'Registro de trabajos'!H:H)) | I23: =IF(A23="","",Configuración!B4) | J23: =IF(A23="","",H23-I23) | K23: =IF(A23="","",COUNTIF('Registro de trabajos'!D:D,B23)) | L23: =IF(A23="","",SUMIF('Registro de trabajos'!D:D,B23,'Registro de trabajos'!G:G)) | M23: =IF(A23="","",IF(D23="","EN USO","FINALIZADO"))
A24: =IF('Control de rollos'!D22<>"","B","") | B24: =IF(A24="","",A24&"-"&TEXT(COUNTIF($A$2:A24,A24),"000")) | C24: =IF(A24="","",D22) | E24: =IF(A24="","",Configuración!B3) | F24: =IF(A24="","",SUMIF('Registro de trabajos'!F:F,B24,'Registro de trabajos'!G:G)) | G24: =IF(A24="","",MAX(0,E24-F24)) | H24: =IF(A24="","",0) | I24: =IF(A24="","",0) | J24: =IF(A24="","",H24-I24) | K24: =IF(A24="","",COUNTIF('Registro de trabajos'!F:F,B24)) | L24: =IF(A24="","",F24) | M24: =IF(A24="","",IF(D24="","EN USO","FINALIZADO"))
A25: =IF('Control de rollos'!D22<>"","A","") | B25: =IF(A25="","",A25&"-"&TEXT(COUNTIF($A$2:A25,A25),"000")) | C25: =IF(A25="","",D22) | E25: =IF(A25="","",Configuración!B3) | F25: =IF(A25="","",SUMIF('Registro de trabajos'!D:D,B25,'Registro de trabajos'!E:E)) | G25: =IF(A25="","",MAX(0,E25-F25)) | H25: =IF(A25="","",SUMIF('Registro de trabajos'!D:D,B25,'Registro de trabajos'!H:H)) | I25: =IF(A25="","",Configuración!B4) | J25: =IF(A25="","",H25-I25) | K25: =IF(A25="","",COUNTIF('Registro de trabajos'!D:D,B25)) | L25: =IF(A25="","",SUMIF('Registro de trabajos'!D:D,B25,'Registro de trabajos'!G:G)) | M25: =IF(A25="","",IF(D25="","EN USO","FINALIZADO"))
A26: =IF('Control de rollos'!D24<>"","B","") | B26: =IF(A26="","",A26&"-"&TEXT(COUNTIF($A$2:A26,A26),"000")) | C26: =IF(A26="","",D24) | E26: =IF(A26="","",Configuración!B3) | F26: =IF(A26="","",SUMIF('Registro de trabajos'!F:F,B26,'Registro de trabajos'!G:G)) | G26: =IF(A26="","",MAX(0,E26-F26)) | H26: =IF(A26="","",0) | I26: =IF(A26="","",0) | J26: =IF(A26="","",H26-I26) | K26: =IF(A26="","",COUNTIF('Registro de trabajos'!F:F,B26)) | L26: =IF(A26="","",F26) | M26: =IF(A26="","",IF(D26="","EN USO","FINALIZADO"))
A27: =IF('Control de rollos'!D24<>"","A","") | B27: =IF(A27="","",A27&"-"&TEXT(COUNTIF($A$2:A27,A27),"000")) | C27: =IF(A27="","",D24) | E27: =IF(A27="","",Configuración!B3) | F27: =IF(A27="","",SUMIF('Registro de trabajos'!D:D,B27,'Registro de trabajos'!E:E)) | G27: =IF(A27="","",MAX(0,E27-F27)) | H27: =IF(A27="","",SUMIF('Registro de trabajos'!D:D,B27,'Registro de trabajos'!H:H)) | I27: =IF(A27="","",Configuración!B4) | J27: =IF(A27="","",H27-I27) | K27: =IF(A27="","",COUNTIF('Registro de trabajos'!D:D,B27)) | L27: =IF(A27="","",SUMIF('Registro de trabajos'!D:D,B27,'Registro de trabajos'!G:G)) | M27: =IF(A27="","",IF(D27="","EN USO","FINALIZADO"))
A28: =IF('Control de rollos'!D26<>"","B","") | B28: =IF(A28="","",A28&"-"&TEXT(COUNTIF($A$2:A28,A28),"000")) | C28: =IF(A28="","",D26) | E28: =IF(A28="","",Configuración!B3) | F28: =IF(A28="","",SUMIF('Registro de trabajos'!F:F,B28,'Registro de trabajos'!G:G)) | G28: =IF(A28="","",MAX(0,E28-F28)) | H28: =IF(A28="","",0) | I28: =IF(A28="","",0) | J28: =IF(A28="","",H28-I28) | K28: =IF(A28="","",COUNTIF('Registro de trabajos'!F:F,B28)) | L28: =IF(A28="","",F28) | M28: =IF(A28="","",IF(D28="","EN USO","FINALIZADO"))
A29: =IF('Control de rollos'!D26<>"","A","") | B29: =IF(A29="","",A29&"-"&TEXT(COUNTIF($A$2:A29,A29),"000")) | C29: =IF(A29="","",D26) | E29: =IF(A29="","",Configuración!B3) | F29: =IF(A29="","",SUMIF('Registro de trabajos'!D:D,B29,'Registro de trabajos'!E:E)) | G29: =IF(A29="","",MAX(0,E29-F29)) | H29: =IF(A29="","",SUMIF('Registro de trabajos'!D:D,B29,'Registro de trabajos'!H:H)) | I29: =IF(A29="","",Configuración!B4) | J29: =IF(A29="","",H29-I29) | K29: =IF(A29="","",COUNTIF('Registro de trabajos'!D:D,B29)) | L29: =IF(A29="","",SUMIF('Registro de trabajos'!D:D,B29,'Registro de trabajos'!G:G)) | M29: =IF(A29="","",IF(D29="","EN USO","FINALIZADO"))
A30: =IF('Control de rollos'!D28<>"","B","") | B30: =IF(A30="","",A30&"-"&TEXT(COUNTIF($A$2:A30,A30),"000")) | C30: =IF(A30="","",D28) | E30: =IF(A30="","",Configuración!B3) | F30: =IF(A30="","",SUMIF('Registro de trabajos'!F:F,B30,'Registro de trabajos'!G:G)) | G30: =IF(A30="","",MAX(0,E30-F30)) | H30: =IF(A30="","",0) | I30: =IF(A30="","",0) | J30: =IF(A30="","",H30-I30) | K30: =IF(A30="","",COUNTIF('Registro de trabajos'!F:F,B30)) | L30: =IF(A30="","",F30) | M30: =IF(A30="","",IF(D30="","EN USO","FINALIZADO"))
A31: =IF('Control de rollos'!D28<>"","A","") | B31: =IF(A31="","",A31&"-"&TEXT(COUNTIF($A$2:A31,A31),"000")) | C31: =IF(A31="","",D28) | E31: =IF(A31="","",Configuración!B3) | F31: =IF(A31="","",SUMIF('Registro de trabajos'!D:D,B31,'Registro de trabajos'!E:E)) | G31: =IF(A31="","",MAX(0,E31-F31)) | H31: =IF(A31="","",SUMIF('Registro de trabajos'!D:D,B31,'Registro de trabajos'!H:H)) | I31: =IF(A31="","",Configuración!B4) | J31: =IF(A31="","",H31-I31) | K31: =IF(A31="","",COUNTIF('Registro de trabajos'!D:D,B31)) | L31: =IF(A31="","",SUMIF('Registro de trabajos'!D:D,B31,'Registro de trabajos'!G:G)) | M31: =IF(A31="","",IF(D31="","EN USO","FINALIZADO"))
A32: =IF('Control de rollos'!D30<>"","B","") | B32: =IF(A32="","",A32&"-"&TEXT(COUNTIF($A$2:A32,A32),"000")) | C32: =IF(A32="","",D30) | E32: =IF(A32="","",Configuración!B3) | F32: =IF(A32="","",SUMIF('Registro de trabajos'!F:F,B32,'Registro de trabajos'!G:G)) | G32: =IF(A32="","",MAX(0,E32-F32)) | H32: =IF(A32="","",0) | I32: =IF(A32="","",0) | J32: =IF(A32="","",H32-I32) | K32: =IF(A32="","",COUNTIF('Registro de trabajos'!F:F,B32)) | L32: =IF(A32="","",F32) | M32: =IF(A32="","",IF(D32="","EN USO","FINALIZADO"))
A33: =IF('Control de rollos'!D30<>"","A","") | B33: =IF(A33="","",A33&"-"&TEXT(COUNTIF($A$2:A33,A33),"000")) | C33: =IF(A33="","",D30) | E33: =IF(A33="","",Configuración!B3) | F33: =IF(A33="","",SUMIF('Registro de trabajos'!D:D,B33,'Registro de trabajos'!E:E)) | G33: =IF(A33="","",MAX(0,E33-F33)) | H33: =IF(A33="","",SUMIF('Registro de trabajos'!D:D,B33,'Registro de trabajos'!H:H)) | I33: =IF(A33="","",Configuración!B4) | J33: =IF(A33="","",H33-I33) | K33: =IF(A33="","",COUNTIF('Registro de trabajos'!D:D,B33)) | L33: =IF(A33="","",SUMIF('Registro de trabajos'!D:D,B33,'Registro de trabajos'!G:G)) | M33: =IF(A33="","",IF(D33="","EN USO","FINALIZADO"))
A34: =IF('Control de rollos'!D32<>"","B","") | B34: =IF(A34="","",A34&"-"&TEXT(COUNTIF($A$2:A34,A34),"000")) | C34: =IF(A34="","",D32) | E34: =IF(A34="","",Configuración!B3) | F34: =IF(A34="","",SUMIF('Registro de trabajos'!F:F,B34,'Registro de trabajos'!G:G)) | G34: =IF(A34="","",MAX(0,E34-F34)) | H34: =IF(A34="","",0) | I34: =IF(A34="","",0) | J34: =IF(A34="","",H34-I34) | K34: =IF(A34="","",COUNTIF('Registro de trabajos'!F:F,B34)) | L34: =IF(A34="","",F34) | M34: =IF(A34="","",IF(D34="","EN USO","FINALIZADO"))
A35: =IF('Control de rollos'!D32<>"","A","") | B35: =IF(A35="","",A35&"-"&TEXT(COUNTIF($A$2:A35,A35),"000")) | C35: =IF(A35="","",D32) | E35: =IF(A35="","",Configuración!B3) | F35: =IF(A35="","",SUMIF('Registro de trabajos'!D:D,B35,'Registro de trabajos'!E:E)) | G35: =IF(A35="","",MAX(0,E35-F35)) | H35: =IF(A35="","",SUMIF('Registro de trabajos'!D:D,B35,'Registro de trabajos'!H:H)) | I35: =IF(A35="","",Configuración!B4) | J35: =IF(A35="","",H35-I35) | K35: =IF(A35="","",COUNTIF('Registro de trabajos'!D:D,B35)) | L35: =IF(A35="","",SUMIF('Registro de trabajos'!D:D,B35,'Registro de trabajos'!G:G)) | M35: =IF(A35="","",IF(D35="","EN USO","FINALIZADO"))
A36: =IF('Control de rollos'!D34<>"","B","") | B36: =IF(A36="","",A36&"-"&TEXT(COUNTIF($A$2:A36,A36),"000")) | C36: =IF(A36="","",D34) | E36: =IF(A36="","",Configuración!B3) | F36: =IF(A36="","",SUMIF('Registro de trabajos'!F:F,B36,'Registro de trabajos'!G:G)) | G36: =IF(A36="","",MAX(0,E36-F36)) | H36: =IF(A36="","",0) | I36: =IF(A36="","",0) | J36: =IF(A36="","",H36-I36) | K36: =IF(A36="","",COUNTIF('Registro de trabajos'!F:F,B36)) | L36: =IF(A36="","",F36) | M36: =IF(A36="","",IF(D36="","EN USO","FINALIZADO"))
A37: =IF('Control de rollos'!D34<>"","A","") | B37: =IF(A37="","",A37&"-"&TEXT(COUNTIF($A$2:A37,A37),"000")) | C37: =IF(A37="","",D34) | E37: =IF(A37="","",Configuración!B3) | F37: =IF(A37="","",SUMIF('Registro de trabajos'!D:D,B37,'Registro de trabajos'!E:E)) | G37: =IF(A37="","",MAX(0,E37-F37)) | H37: =IF(A37="","",SUMIF('Registro de trabajos'!D:D,B37,'Registro de trabajos'!H:H)) | I37: =IF(A37="","",Configuración!B4) | J37: =IF(A37="","",H37-I37) | K37: =IF(A37="","",COUNTIF('Registro de trabajos'!D:D,B37)) | L37: =IF(A37="","",SUMIF('Registro de trabajos'!D:D,B37,'Registro de trabajos'!G:G)) | M37: =IF(A37="","",IF(D37="","EN USO","FINALIZADO"))
A38: =IF('Control de rollos'!D36<>"","B","") | B38: =IF(A38="","",A38&"-"&TEXT(COUNTIF($A$2:A38,A38),"000")) | C38: =IF(A38="","",D36) | E38: =IF(A38="","",Configuración!B3) | F38: =IF(A38="","",SUMIF('Registro de trabajos'!F:F,B38,'Registro de trabajos'!G:G)) | G38: =IF(A38="","",MAX(0,E38-F38)) | H38: =IF(A38="","",0) | I38: =IF(A38="","",0) | J38: =IF(A38="","",H38-I38) | K38: =IF(A38="","",COUNTIF('Registro de trabajos'!F:F,B38)) | L38: =IF(A38="","",F38) | M38: =IF(A38="","",IF(D38="","EN USO","FINALIZADO"))
A39: =IF('Control de rollos'!D36<>"","A","") | B39: =IF(A39="","",A39&"-"&TEXT(COUNTIF($A$2:A39,A39),"000")) | C39: =IF(A39="","",D36) | E39: =IF(A39="","",Configuración!B3) | F39: =IF(A39="","",SUMIF('Registro de trabajos'!D:D,B39,'Registro de trabajos'!E:E)) | G39: =IF(A39="","",MAX(0,E39-F39)) | H39: =IF(A39="","",SUMIF('Registro de trabajos'!D:D,B39,'Registro de trabajos'!H:H)) | I39: =IF(A39="","",Configuración!B4) | J39: =IF(A39="","",H39-I39) | K39: =IF(A39="","",COUNTIF('Registro de trabajos'!D:D,B39)) | L39: =IF(A39="","",SUMIF('Registro de trabajos'!D:D,B39,'Registro de trabajos'!G:G)) | M39: =IF(A39="","",IF(D39="","EN USO","FINALIZADO"))
A40: =IF('Control de rollos'!D38<>"","B","") | B40: =IF(A40="","",A40&"-"&TEXT(COUNTIF($A$2:A40,A40),"000")) | C40: =IF(A40="","",D38) | E40: =IF(A40="","",Configuración!B3) | F40: =IF(A40="","",SUMIF('Registro de trabajos'!F:F,B40,'Registro de trabajos'!G:G)) | G40: =IF(A40="","",MAX(0,E40-F40)) | H40: =IF(A40="","",0) | I40: =IF(A40="","",0) | J40: =IF(A40="","",H40-I40) | K40: =IF(A40="","",COUNTIF('Registro de trabajos'!F:F,B40)) | L40: =IF(A40="","",F40) | M40: =IF(A40="","",IF(D40="","EN USO","FINALIZADO"))
A41: =IF('Control de rollos'!D38<>"","A","") | B41: =IF(A41="","",A41&"-"&TEXT(COUNTIF($A$2:A41,A41),"000")) | C41: =IF(A41="","",D38) | E41: =IF(A41="","",Configuración!B3) | F41: =IF(A41="","",SUMIF('Registro de trabajos'!D:D,B41,'Registro de trabajos'!E:E)) | G41: =IF(A41="","",MAX(0,E41-F41)) | H41: =IF(A41="","",SUMIF('Registro de trabajos'!D:D,B41,'Registro de trabajos'!H:H)) | I41: =IF(A41="","",Configuración!B4) | J41: =IF(A41="","",H41-I41) | K41: =IF(A41="","",COUNTIF('Registro de trabajos'!D:D,B41)) | L41: =IF(A41="","",SUMIF('Registro de trabajos'!D:D,B41,'Registro de trabajos'!G:G)) | M41: =IF(A41="","",IF(D41="","EN USO","FINALIZADO"))
A42: =IF('Control de rollos'!D40<>"","B","") | B42: =IF(A42="","",A42&"-"&TEXT(COUNTIF($A$2:A42,A42),"000")) | C42: =IF(A42="","",D40) | E42: =IF(A42="","",Configuración!B3) | F42: =IF(A42="","",SUMIF('Registro de trabajos'!F:F,B42,'Registro de trabajos'!G:G)) | G42: =IF(A42="","",MAX(0,E42-F42)) | H42: =IF(A42="","",0) | I42: =IF(A42="","",0) | J42: =IF(A42="","",H42-I42) | K42: =IF(A42="","",COUNTIF('Registro de trabajos'!F:F,B42)) | L42: =IF(A42="","",F42) | M42: =IF(A42="","",IF(D42="","EN USO","FINALIZADO"))
A43: =IF('Control de rollos'!D40<>"","A","") | B43: =IF(A43="","",A43&"-"&TEXT(COUNTIF($A$2:A43,A43),"000")) | C43: =IF(A43="","",D40) | E43: =IF(A43="","",Configuración!B3) | F43: =IF(A43="","",SUMIF('Registro de trabajos'!D:D,B43,'Registro de trabajos'!E:E)) | G43: =IF(A43="","",MAX(0,E43-F43)) | H43: =IF(A43="","",SUMIF('Registro de trabajos'!D:D,B43,'Registro de trabajos'!H:H)) | I43: =IF(A43="","",Configuración!B4) | J43: =IF(A43="","",H43-I43) | K43: =IF(A43="","",COUNTIF('Registro de trabajos'!D:D,B43)) | L43: =IF(A43="","",SUMIF('Registro de trabajos'!D:D,B43,'Registro de trabajos'!G:G)) | M43: =IF(A43="","",IF(D43="","EN USO","FINALIZADO"))
A44: =IF('Control de rollos'!D42<>"","B","") | B44: =IF(A44="","",A44&"-"&TEXT(COUNTIF($A$2:A44,A44),"000")) | C44: =IF(A44="","",D42) | E44: =IF(A44="","",Configuración!B3) | F44: =IF(A44="","",SUMIF('Registro de trabajos'!F:F,B44,'Registro de trabajos'!G:G)) | G44: =IF(A44="","",MAX(0,E44-F44)) | H44: =IF(A44="","",0) | I44: =IF(A44="","",0) | J44: =IF(A44="","",H44-I44) | K44: =IF(A44="","",COUNTIF('Registro de trabajos'!F:F,B44)) | L44: =IF(A44="","",F44) | M44: =IF(A44="","",IF(D44="","EN USO","FINALIZADO"))
A45: =IF('Control de rollos'!D42<>"","A","") | B45: =IF(A45="","",A45&"-"&TEXT(COUNTIF($A$2:A45,A45),"000")) | C45: =IF(A45="","",D42) | E45: =IF(A45="","",Configuración!B3) | F45: =IF(A45="","",SUMIF('Registro de trabajos'!D:D,B45,'Registro de trabajos'!E:E)) | G45: =IF(A45="","",MAX(0,E45-F45)) | H45: =IF(A45="","",SUMIF('Registro de trabajos'!D:D,B45,'Registro de trabajos'!H:H)) | I45: =IF(A45="","",Configuración!B4) | J45: =IF(A45="","",H45-I45) | K45: =IF(A45="","",COUNTIF('Registro de trabajos'!D:D,B45)) | L45: =IF(A45="","",SUMIF('Registro de trabajos'!D:D,B45,'Registro de trabajos'!G:G)) | M45: =IF(A45="","",IF(D45="","EN USO","FINALIZADO"))
A46: =IF('Control de rollos'!D44<>"","B","") | B46: =IF(A46="","",A46&"-"&TEXT(COUNTIF($A$2:A46,A46),"000")) | C46: =IF(A46="","",D44) | E46: =IF(A46="","",Configuración!B3) | F46: =IF(A46="","",SUMIF('Registro de trabajos'!F:F,B46,'Registro de trabajos'!G:G)) | G46: =IF(A46="","",MAX(0,E46-F46)) | H46: =IF(A46="","",0) | I46: =IF(A46="","",0) | J46: =IF(A46="","",H46-I46) | K46: =IF(A46="","",COUNTIF('Registro de trabajos'!F:F,B46)) | L46: =IF(A46="","",F46) | M46: =IF(A46="","",IF(D46="","EN USO","FINALIZADO"))
A47: =IF('Control de rollos'!D44<>"","A","") | B47: =IF(A47="","",A47&"-"&TEXT(COUNTIF($A$2:A47,A47),"000")) | C47: =IF(A47="","",D44) | E47: =IF(A47="","",Configuración!B3) | F47: =IF(A47="","",SUMIF('Registro de trabajos'!D:D,B47,'Registro de trabajos'!E:E)) | G47: =IF(A47="","",MAX(0,E47-F47)) | H47: =IF(A47="","",SUMIF('Registro de trabajos'!D:D,B47,'Registro de trabajos'!H:H)) | I47: =IF(A47="","",Configuración!B4) | J47: =IF(A47="","",H47-I47) | K47: =IF(A47="","",COUNTIF('Registro de trabajos'!D:D,B47)) | L47: =IF(A47="","",SUMIF('Registro de trabajos'!D:D,B47,'Registro de trabajos'!G:G)) | M47: =IF(A47="","",IF(D47="","EN USO","FINALIZADO"))
A48: =IF('Control de rollos'!D46<>"","B","") | B48: =IF(A48="","",A48&"-"&TEXT(COUNTIF($A$2:A48,A48),"000")) | C48: =IF(A48="","",D46) | E48: =IF(A48="","",Configuración!B3) | F48: =IF(A48="","",SUMIF('Registro de trabajos'!F:F,B48,'Registro de trabajos'!G:G)) | G48: =IF(A48="","",MAX(0,E48-F48)) | H48: =IF(A48="","",0) | I48: =IF(A48="","",0) | J48: =IF(A48="","",H48-I48) | K48: =IF(A48="","",COUNTIF('Registro de trabajos'!F:F,B48)) | L48: =IF(A48="","",F48) | M48: =IF(A48="","",IF(D48="","EN USO","FINALIZADO"))
A49: =IF('Control de rollos'!D46<>"","A","") | B49: =IF(A49="","",A49&"-"&TEXT(COUNTIF($A$2:A49,A49),"000")) | C49: =IF(A49="","",D46) | E49: =IF(A49="","",Configuración!B3) | F49: =IF(A49="","",SUMIF('Registro de trabajos'!D:D,B49,'Registro de trabajos'!E:E)) | G49: =IF(A49="","",MAX(0,E49-F49)) | H49: =IF(A49="","",SUMIF('Registro de trabajos'!D:D,B49,'Registro de trabajos'!H:H)) | I49: =IF(A49="","",Configuración!B4) | J49: =IF(A49="","",H49-I49) | K49: =IF(A49="","",COUNTIF('Registro de trabajos'!D:D,B49)) | L49: =IF(A49="","",SUMIF('Registro de trabajos'!D:D,B49,'Registro de trabajos'!G:G)) | M49: =IF(A49="","",IF(D49="","EN USO","FINALIZADO"))
A50: =IF('Control de rollos'!D48<>"","B","") | B50: =IF(A50="","",A50&"-"&TEXT(COUNTIF($A$2:A50,A50),"000")) | C50: =IF(A50="","",D48) | E50: =IF(A50="","",Configuración!B3) | F50: =IF(A50="","",SUMIF('Registro de trabajos'!F:F,B50,'Registro de trabajos'!G:G)) | G50: =IF(A50="","",MAX(0,E50-F50)) | H50: =IF(A50="","",0) | I50: =IF(A50="","",0) | J50: =IF(A50="","",H50-I50) | K50: =IF(A50="","",COUNTIF('Registro de trabajos'!F:F,B50)) | L50: =IF(A50="","",F50) | M50: =IF(A50="","",IF(D50="","EN USO","FINALIZADO"))
A51: =IF('Control de rollos'!D48<>"","A","") | B51: =IF(A51="","",A51&"-"&TEXT(COUNTIF($A$2:A51,A51),"000")) | C51: =IF(A51="","",D48) | E51: =IF(A51="","",Configuración!B3) | F51: =IF(A51="","",SUMIF('Registro de trabajos'!D:D,B51,'Registro de trabajos'!E:E)) | G51: =IF(A51="","",MAX(0,E51-F51)) | H51: =IF(A51="","",SUMIF('Registro de trabajos'!D:D,B51,'Registro de trabajos'!H:H)) | I51: =IF(A51="","",Configuración!B4) | J51: =IF(A51="","",H51-I51) | K51: =IF(A51="","",COUNTIF('Registro de trabajos'!D:D,B51)) | L51: =IF(A51="","",SUMIF('Registro de trabajos'!D:D,B51,'Registro de trabajos'!G:G)) | M51: =IF(A51="","",IF(D51="","EN USO","FINALIZADO"))
A52: =IF('Control de rollos'!D50<>"","B","") | B52: =IF(A52="","",A52&"-"&TEXT(COUNTIF($A$2:A52,A52),"000")) | C52: =IF(A52="","",D50) | E52: =IF(A52="","",Configuración!B3) | F52: =IF(A52="","",SUMIF('Registro de trabajos'!F:F,B52,'Registro de trabajos'!G:G)) | G52: =IF(A52="","",MAX(0,E52-F52)) | H52: =IF(A52="","",0) | I52: =IF(A52="","",0) | J52: =IF(A52="","",H52-I52) | K52: =IF(A52="","",COUNTIF('Registro de trabajos'!F:F,B52)) | L52: =IF(A52="","",F52) | M52: =IF(A52="","",IF(D52="","EN USO","FINALIZADO"))
A53: =IF('Control de rollos'!D50<>"","A","") | B53: =IF(A53="","",A53&"-"&TEXT(COUNTIF($A$2:A53,A53),"000")) | C53: =IF(A53="","",D50) | E53: =IF(A53="","",Configuración!B3) | F53: =IF(A53="","",SUMIF('Registro de trabajos'!D:D,B53,'Registro de trabajos'!E:E)) | G53: =IF(A53="","",MAX(0,E53-F53)) | H53: =IF(A53="","",SUMIF('Registro de trabajos'!D:D,B53,'Registro de trabajos'!H:H)) | I53: =IF(A53="","",Configuración!B4) | J53: =IF(A53="","",H53-I53) | K53: =IF(A53="","",COUNTIF('Registro de trabajos'!D:D,B53)) | L53: =IF(A53="","",SUMIF('Registro de trabajos'!D:D,B53,'Registro de trabajos'!G:G)) | M53: =IF(A53="","",IF(D53="","EN USO","FINALIZADO"))
A54: =IF('Control de rollos'!D52<>"","B","") | B54: =IF(A54="","",A54&"-"&TEXT(COUNTIF($A$2:A54,A54),"000")) | C54: =IF(A54="","",D52) | E54: =IF(A54="","",Configuración!B3) | F54: =IF(A54="","",SUMIF('Registro de trabajos'!F:F,B54,'Registro de trabajos'!G:G)) | G54: =IF(A54="","",MAX(0,E54-F54)) | H54: =IF(A54="","",0) | I54: =IF(A54="","",0) | J54: =IF(A54="","",H54-I54) | K54: =IF(A54="","",COUNTIF('Registro de trabajos'!F:F,B54)) | L54: =IF(A54="","",F54) | M54: =IF(A54="","",IF(D54="","EN USO","FINALIZADO"))
A55: =IF('Control de rollos'!D52<>"","A","") | B55: =IF(A55="","",A55&"-"&TEXT(COUNTIF($A$2:A55,A55),"000")) | C55: =IF(A55="","",D52) | E55: =IF(A55="","",Configuración!B3) | F55: =IF(A55="","",SUMIF('Registro de trabajos'!D:D,B55,'Registro de trabajos'!E:E)) | G55: =IF(A55="","",MAX(0,E55-F55)) | H55: =IF(A55="","",SUMIF('Registro de trabajos'!D:D,B55,'Registro de trabajos'!H:H)) | I55: =IF(A55="","",Configuración!B4) | J55: =IF(A55="","",H55-I55) | K55: =IF(A55="","",COUNTIF('Registro de trabajos'!D:D,B55)) | L55: =IF(A55="","",SUMIF('Registro de trabajos'!D:D,B55,'Registro de trabajos'!G:G)) | M55: =IF(A55="","",IF(D55="","EN USO","FINALIZADO"))
A56: =IF('Control de rollos'!D54<>"","B","") | B56: =IF(A56="","",A56&"-"&TEXT(COUNTIF($A$2:A56,A56),"000")) | C56: =IF(A56="","",D54) | E56: =IF(A56="","",Configuración!B3) | F56: =IF(A56="","",SUMIF('Registro de trabajos'!F:F,B56,'Registro de trabajos'!G:G)) | G56: =IF(A56="","",MAX(0,E56-F56)) | H56: =IF(A56="","",0) | I56: =IF(A56="","",0) | J56: =IF(A56="","",H56-I56) | K56: =IF(A56="","",COUNTIF('Registro de trabajos'!F:F,B56)) | L56: =IF(A56="","",F56) | M56: =IF(A56="","",IF(D56="","EN USO","FINALIZADO"))
A57: =IF('Control de rollos'!D54<>"","A","") | B57: =IF(A57="","",A57&"-"&TEXT(COUNTIF($A$2:A57,A57),"000")) | C57: =IF(A57="","",D54) | E57: =IF(A57="","",Configuración!B3) | F57: =IF(A57="","",SUMIF('Registro de trabajos'!D:D,B57,'Registro de trabajos'!E:E)) | G57: =IF(A57="","",MAX(0,E57-F57)) | H57: =IF(A57="","",SUMIF('Registro de trabajos'!D:D,B57,'Registro de trabajos'!H:H)) | I57: =IF(A57="","",Configuración!B4) | J57: =IF(A57="","",H57-I57) | K57: =IF(A57="","",COUNTIF('Registro de trabajos'!D:D,B57)) | L57: =IF(A57="","",SUMIF('Registro de trabajos'!D:D,B57,'Registro de trabajos'!G:G)) | M57: =IF(A57="","",IF(D57="","EN USO","FINALIZADO"))
A58: =IF('Control de rollos'!D56<>"","B","") | B58: =IF(A58="","",A58&"-"&TEXT(COUNTIF($A$2:A58,A58),"000")) | C58: =IF(A58="","",D56) | E58: =IF(A58="","",Configuración!B3) | F58: =IF(A58="","",SUMIF('Registro de trabajos'!F:F,B58,'Registro de trabajos'!G:G)) | G58: =IF(A58="","",MAX(0,E58-F58)) | H58: =IF(A58="","",0) | I58: =IF(A58="","",0) | J58: =IF(A58="","",H58-I58) | K58: =IF(A58="","",COUNTIF('Registro de trabajos'!F:F,B58)) | L58: =IF(A58="","",F58) | M58: =IF(A58="","",IF(D58="","EN USO","FINALIZADO"))
A59: =IF('Control de rollos'!D56<>"","A","") | B59: =IF(A59="","",A59&"-"&TEXT(COUNTIF($A$2:A59,A59),"000")) | C59: =IF(A59="","",D56) | E59: =IF(A59="","",Configuración!B3) | F59: =IF(A59="","",SUMIF('Registro de trabajos'!D:D,B59,'Registro de trabajos'!E:E)) | G59: =IF(A59="","",MAX(0,E59-F59)) | H59: =IF(A59="","",SUMIF('Registro de trabajos'!D:D,B59,'Registro de trabajos'!H:H)) | I59: =IF(A59="","",Configuración!B4) | J59: =IF(A59="","",H59-I59) | K59: =IF(A59="","",COUNTIF('Registro de trabajos'!D:D,B59)) | L59: =IF(A59="","",SUMIF('Registro de trabajos'!D:D,B59,'Registro de trabajos'!G:G)) | M59: =IF(A59="","",IF(D59="","EN USO","FINALIZADO"))
A60: =IF('Control de rollos'!D58<>"","B","") | B60: =IF(A60="","",A60&"-"&TEXT(COUNTIF($A$2:A60,A60),"000")) | C60: =IF(A60="","",D58) | E60: =IF(A60="","",Configuración!B3) | F60: =IF(A60="","",SUMIF('Registro de trabajos'!F:F,B60,'Registro de trabajos'!G:G)) | G60: =IF(A60="","",MAX(0,E60-F60)) | H60: =IF(A60="","",0) | I60: =IF(A60="","",0) | J60: =IF(A60="","",H60-I60) | K60: =IF(A60="","",COUNTIF('Registro de trabajos'!F:F,B60)) | L60: =IF(A60="","",F60) | M60: =IF(A60="","",IF(D60="","EN USO","FINALIZADO"))
A61: =IF('Control de rollos'!D58<>"","A","") | B61: =IF(A61="","",A61&"-"&TEXT(COUNTIF($A$2:A61,A61),"000")) | C61: =IF(A61="","",D58) | E61: =IF(A61="","",Configuración!B3) | F61: =IF(A61="","",SUMIF('Registro de trabajos'!D:D,B61,'Registro de trabajos'!E:E)) | G61: =IF(A61="","",MAX(0,E61-F61)) | H61: =IF(A61="","",SUMIF('Registro de trabajos'!D:D,B61,'Registro de trabajos'!H:H)) | I61: =IF(A61="","",Configuración!B4) | J61: =IF(A61="","",H61-I61) | K61: =IF(A61="","",COUNTIF('Registro de trabajos'!D:D,B61)) | L61: =IF(A61="","",SUMIF('Registro de trabajos'!D:D,B61,'Registro de trabajos'!G:G)) | M61: =IF(A61="","",IF(D61="","EN USO","FINALIZADO"))
A62: =IF('Control de rollos'!D60<>"","B","") | B62: =IF(A62="","",A62&"-"&TEXT(COUNTIF($A$2:A62,A62),"000")) | C62: =IF(A62="","",D60) | E62: =IF(A62="","",Configuración!B3) | F62: =IF(A62="","",SUMIF('Registro de trabajos'!F:F,B62,'Registro de trabajos'!G:G)) | G62: =IF(A62="","",MAX(0,E62-F62)) | H62: =IF(A62="","",0) | I62: =IF(A62="","",0) | J62: =IF(A62="","",H62-I62) | K62: =IF(A62="","",COUNTIF('Registro de trabajos'!F:F,B62)) | L62: =IF(A62="","",F62) | M62: =IF(A62="","",IF(D62="","EN USO","FINALIZADO"))
A63: =IF('Control de rollos'!D60<>"","A","") | B63: =IF(A63="","",A63&"-"&TEXT(COUNTIF($A$2:A63,A63),"000")) | C63: =IF(A63="","",D60) | E63: =IF(A63="","",Configuración!B3) | F63: =IF(A63="","",SUMIF('Registro de trabajos'!D:D,B63,'Registro de trabajos'!E:E)) | G63: =IF(A63="","",MAX(0,E63-F63)) | H63: =IF(A63="","",SUMIF('Registro de trabajos'!D:D,B63,'Registro de trabajos'!H:H)) | I63: =IF(A63="","",Configuración!B4) | J63: =IF(A63="","",H63-I63) | K63: =IF(A63="","",COUNTIF('Registro de trabajos'!D:D,B63)) | L63: =IF(A63="","",SUMIF('Registro de trabajos'!D:D,B63,'Registro de trabajos'!G:G)) | M63: =IF(A63="","",IF(D63="","EN USO","FINALIZADO"))
A64: =IF('Control de rollos'!D62<>"","B","") | B64: =IF(A64="","",A64&"-"&TEXT(COUNTIF($A$2:A64,A64),"000")) | C64: =IF(A64="","",D62) | E64: =IF(A64="","",Configuración!B3) | F64: =IF(A64="","",SUMIF('Registro de trabajos'!F:F,B64,'Registro de trabajos'!G:G)) | G64: =IF(A64="","",MAX(0,E64-F64)) | H64: =IF(A64="","",0) | I64: =IF(A64="","",0) | J64: =IF(A64="","",H64-I64) | K64: =IF(A64="","",COUNTIF('Registro de trabajos'!F:F,B64)) | L64: =IF(A64="","",F64) | M64: =IF(A64="","",IF(D64="","EN USO","FINALIZADO"))
A65: =IF('Control de rollos'!D62<>"","A","") | B65: =IF(A65="","",A65&"-"&TEXT(COUNTIF($A$2:A65,A65),"000")) | C65: =IF(A65="","",D62) | E65: =IF(A65="","",Configuración!B3) | F65: =IF(A65="","",SUMIF('Registro de trabajos'!D:D,B65,'Registro de trabajos'!E:E)) | G65: =IF(A65="","",MAX(0,E65-F65)) | H65: =IF(A65="","",SUMIF('Registro de trabajos'!D:D,B65,'Registro de trabajos'!H:H)) | I65: =IF(A65="","",Configuración!B4) | J65: =IF(A65="","",H65-I65) | K65: =IF(A65="","",COUNTIF('Registro de trabajos'!D:D,B65)) | L65: =IF(A65="","",SUMIF('Registro de trabajos'!D:D,B65,'Registro de trabajos'!G:G)) | M65: =IF(A65="","",IF(D65="","EN USO","FINALIZADO"))
A66: =IF('Control de rollos'!D64<>"","B","") | B66: =IF(A66="","",A66&"-"&TEXT(COUNTIF($A$2:A66,A66),"000")) | C66: =IF(A66="","",D64) | E66: =IF(A66="","",Configuración!B3) | F66: =IF(A66="","",SUMIF('Registro de trabajos'!F:F,B66,'Registro de trabajos'!G:G)) | G66: =IF(A66="","",MAX(0,E66-F66)) | H66: =IF(A66="","",0) | I66: =IF(A66="","",0) | J66: =IF(A66="","",H66-I66) | K66: =IF(A66="","",COUNTIF('Registro de trabajos'!F:F,B66)) | L66: =IF(A66="","",F66) | M66: =IF(A66="","",IF(D66="","EN USO","FINALIZADO"))
A67: =IF('Control de rollos'!D64<>"","A","") | B67: =IF(A67="","",A67&"-"&TEXT(COUNTIF($A$2:A67,A67),"000")) | C67: =IF(A67="","",D64) | E67: =IF(A67="","",Configuración!B3) | F67: =IF(A67="","",SUMIF('Registro de trabajos'!D:D,B67,'Registro de trabajos'!E:E)) | G67: =IF(A67="","",MAX(0,E67-F67)) | H67: =IF(A67="","",SUMIF('Registro de trabajos'!D:D,B67,'Registro de trabajos'!H:H)) | I67: =IF(A67="","",Configuración!B4) | J67: =IF(A67="","",H67-I67) | K67: =IF(A67="","",COUNTIF('Registro de trabajos'!D:D,B67)) | L67: =IF(A67="","",SUMIF('Registro de trabajos'!D:D,B67,'Registro de trabajos'!G:G)) | M67: =IF(A67="","",IF(D67="","EN USO","FINALIZADO"))
A68: =IF('Control de rollos'!D66<>"","B","") | B68: =IF(A68="","",A68&"-"&TEXT(COUNTIF($A$2:A68,A68),"000")) | C68: =IF(A68="","",D66) | E68: =IF(A68="","",Configuración!B3) | F68: =IF(A68="","",SUMIF('Registro de trabajos'!F:F,B68,'Registro de trabajos'!G:G)) | G68: =IF(A68="","",MAX(0,E68-F68)) | H68: =IF(A68="","",0) | I68: =IF(A68="","",0) | J68: =IF(A68="","",H68-I68) | K68: =IF(A68="","",COUNTIF('Registro de trabajos'!F:F,B68)) | L68: =IF(A68="","",F68) | M68: =IF(A68="","",IF(D68="","EN USO","FINALIZADO"))
A69: =IF('Control de rollos'!D66<>"","A","") | B69: =IF(A69="","",A69&"-"&TEXT(COUNTIF($A$2:A69,A69),"000")) | C69: =IF(A69="","",D66) | E69: =IF(A69="","",Configuración!B3) | F69: =IF(A69="","",SUMIF('Registro de trabajos'!D:D,B69,'Registro de trabajos'!E:E)) | G69: =IF(A69="","",MAX(0,E69-F69)) | H69: =IF(A69="","",SUMIF('Registro de trabajos'!D:D,B69,'Registro de trabajos'!H:H)) | I69: =IF(A69="","",Configuración!B4) | J69: =IF(A69="","",H69-I69) | K69: =IF(A69="","",COUNTIF('Registro de trabajos'!D:D,B69)) | L69: =IF(A69="","",SUMIF('Registro de trabajos'!D:D,B69,'Registro de trabajos'!G:G)) | M69: =IF(A69="","",IF(D69="","EN USO","FINALIZADO"))
A70: =IF('Control de rollos'!D68<>"","B","") | B70: =IF(A70="","",A70&"-"&TEXT(COUNTIF($A$2:A70,A70),"000")) | C70: =IF(A70="","",D68) | E70: =IF(A70="","",Configuración!B3) | F70: =IF(A70="","",SUMIF('Registro de trabajos'!F:F,B70,'Registro de trabajos'!G:G)) | G70: =IF(A70="","",MAX(0,E70-F70)) | H70: =IF(A70="","",0) | I70: =IF(A70="","",0) | J70: =IF(A70="","",H70-I70) | K70: =IF(A70="","",COUNTIF('Registro de trabajos'!F:F,B70)) | L70: =IF(A70="","",F70) | M70: =IF(A70="","",IF(D70="","EN USO","FINALIZADO"))
A71: =IF('Control de rollos'!D68<>"","A","") | B71: =IF(A71="","",A71&"-"&TEXT(COUNTIF($A$2:A71,A71),"000")) | C71: =IF(A71="","",D68) | E71: =IF(A71="","",Configuración!B3) | F71: =IF(A71="","",SUMIF('Registro de trabajos'!D:D,B71,'Registro de trabajos'!E:E)) | G71: =IF(A71="","",MAX(0,E71-F71)) | H71: =IF(A71="","",SUMIF('Registro de trabajos'!D:D,B71,'Registro de trabajos'!H:H)) | I71: =IF(A71="","",Configuración!B4) | J71: =IF(A71="","",H71-I71) | K71: =IF(A71="","",COUNTIF('Registro de trabajos'!D:D,B71)) | L71: =IF(A71="","",SUMIF('Registro de trabajos'!D:D,B71,'Registro de trabajos'!G:G)) | M71: =IF(A71="","",IF(D71="","EN USO","FINALIZADO"))
A72: =IF('Control de rollos'!D70<>"","B","") | B72: =IF(A72="","",A72&"-"&TEXT(COUNTIF($A$2:A72,A72),"000")) | C72: =IF(A72="","",D70) | E72: =IF(A72="","",Configuración!B3) | F72: =IF(A72="","",SUMIF('Registro de trabajos'!F:F,B72,'Registro de trabajos'!G:G)) | G72: =IF(A72="","",MAX(0,E72-F72)) | H72: =IF(A72="","",0) | I72: =IF(A72="","",0) | J72: =IF(A72="","",H72-I72) | K72: =IF(A72="","",COUNTIF('Registro de trabajos'!F:F,B72)) | L72: =IF(A72="","",F72) | M72: =IF(A72="","",IF(D72="","EN USO","FINALIZADO"))
A73: =IF('Control de rollos'!D70<>"","A","") | B73: =IF(A73="","",A73&"-"&TEXT(COUNTIF($A$2:A73,A73),"000")) | C73: =IF(A73="","",D70) | E73: =IF(A73="","",Configuración!B3) | F73: =IF(A73="","",SUMIF('Registro de trabajos'!D:D,B73,'Registro de trabajos'!E:E)) | G73: =IF(A73="","",MAX(0,E73-F73)) | H73: =IF(A73="","",SUMIF('Registro de trabajos'!D:D,B73,'Registro de trabajos'!H:H)) | I73: =IF(A73="","",Configuración!B4) | J73: =IF(A73="","",H73-I73) | K73: =IF(A73="","",COUNTIF('Registro de trabajos'!D:D,B73)) | L73: =IF(A73="","",SUMIF('Registro de trabajos'!D:D,B73,'Registro de trabajos'!G:G)) | M73: =IF(A73="","",IF(D73="","EN USO","FINALIZADO"))
A74: =IF('Control de rollos'!D72<>"","B","") | B74: =IF(A74="","",A74&"-"&TEXT(COUNTIF($A$2:A74,A74),"000")) | C74: =IF(A74="","",D72) | E74: =IF(A74="","",Configuración!B3) | F74: =IF(A74="","",SUMIF('Registro de trabajos'!F:F,B74,'Registro de trabajos'!G:G)) | G74: =IF(A74="","",MAX(0,E74-F74)) | H74: =IF(A74="","",0) | I74: =IF(A74="","",0) | J74: =IF(A74="","",H74-I74) | K74: =IF(A74="","",COUNTIF('Registro de trabajos'!F:F,B74)) | L74: =IF(A74="","",F74) | M74: =IF(A74="","",IF(D74="","EN USO","FINALIZADO"))
A75: =IF('Control de rollos'!D72<>"","A","") | B75: =IF(A75="","",A75&"-"&TEXT(COUNTIF($A$2:A75,A75),"000")) | C75: =IF(A75="","",D72) | E75: =IF(A75="","",Configuración!B3) | F75: =IF(A75="","",SUMIF('Registro de trabajos'!D:D,B75,'Registro de trabajos'!E:E)) | G75: =IF(A75="","",MAX(0,E75-F75)) | H75: =IF(A75="","",SUMIF('Registro de trabajos'!D:D,B75,'Registro de trabajos'!H:H)) | I75: =IF(A75="","",Configuración!B4) | J75: =IF(A75="","",H75-I75) | K75: =IF(A75="","",COUNTIF('Registro de trabajos'!D:D,B75)) | L75: =IF(A75="","",SUMIF('Registro de trabajos'!D:D,B75,'Registro de trabajos'!G:G)) | M75: =IF(A75="","",IF(D75="","EN USO","FINALIZADO"))
A76: =IF('Control de rollos'!D74<>"","B","") | B76: =IF(A76="","",A76&"-"&TEXT(COUNTIF($A$2:A76,A76),"000")) | C76: =IF(A76="","",D74) | E76: =IF(A76="","",Configuración!B3) | F76: =IF(A76="","",SUMIF('Registro de trabajos'!F:F,B76,'Registro de trabajos'!G:G)) | G76: =IF(A76="","",MAX(0,E76-F76)) | H76: =IF(A76="","",0) | I76: =IF(A76="","",0) | J76: =IF(A76="","",H76-I76) | K76: =IF(A76="","",COUNTIF('Registro de trabajos'!F:F,B76)) | L76: =IF(A76="","",F76) | M76: =IF(A76="","",IF(D76="","EN USO","FINALIZADO"))
A77: =IF('Control de rollos'!D74<>"","A","") | B77: =IF(A77="","",A77&"-"&TEXT(COUNTIF($A$2:A77,A77),"000")) | C77: =IF(A77="","",D74) | E77: =IF(A77="","",Configuración!B3) | F77: =IF(A77="","",SUMIF('Registro de trabajos'!D:D,B77,'Registro de trabajos'!E:E)) | G77: =IF(A77="","",MAX(0,E77-F77)) | H77: =IF(A77="","",SUMIF('Registro de trabajos'!D:D,B77,'Registro de trabajos'!H:H)) | I77: =IF(A77="","",Configuración!B4) | J77: =IF(A77="","",H77-I77) | K77: =IF(A77="","",COUNTIF('Registro de trabajos'!D:D,B77)) | L77: =IF(A77="","",SUMIF('Registro de trabajos'!D:D,B77,'Registro de trabajos'!G:G)) | M77: =IF(A77="","",IF(D77="","EN USO","FINALIZADO"))
A78: =IF('Control de rollos'!D76<>"","B","") | B78: =IF(A78="","",A78&"-"&TEXT(COUNTIF($A$2:A78,A78),"000")) | C78: =IF(A78="","",D76) | E78: =IF(A78="","",Configuración!B3) | F78: =IF(A78="","",SUMIF('Registro de trabajos'!F:F,B78,'Registro de trabajos'!G:G)) | G78: =IF(A78="","",MAX(0,E78-F78)) | H78: =IF(A78="","",0) | I78: =IF(A78="","",0) | J78: =IF(A78="","",H78-I78) | K78: =IF(A78="","",COUNTIF('Registro de trabajos'!F:F,B78)) | L78: =IF(A78="","",F78) | M78: =IF(A78="","",IF(D78="","EN USO","FINALIZADO"))
A79: =IF('Control de rollos'!D76<>"","A","") | B79: =IF(A79="","",A79&"-"&TEXT(COUNTIF($A$2:A79,A79),"000")) | C79: =IF(A79="","",D76) | E79: =IF(A79="","",Configuración!B3) | F79: =IF(A79="","",SUMIF('Registro de trabajos'!D:D,B79,'Registro de trabajos'!E:E)) | G79: =IF(A79="","",MAX(0,E79-F79)) | H79: =IF(A79="","",SUMIF('Registro de trabajos'!D:D,B79,'Registro de trabajos'!H:H)) | I79: =IF(A79="","",Configuración!B4) | J79: =IF(A79="","",H79-I79) | K79: =IF(A79="","",COUNTIF('Registro de trabajos'!D:D,B79)) | L79: =IF(A79="","",SUMIF('Registro de trabajos'!D:D,B79,'Registro de trabajos'!G:G)) | M79: =IF(A79="","",IF(D79="","EN USO","FINALIZADO"))
A80: =IF('Control de rollos'!D78<>"","B","") | B80: =IF(A80="","",A80&"-"&TEXT(COUNTIF($A$2:A80,A80),"000")) | C80: =IF(A80="","",D78) | E80: =IF(A80="","",Configuración!B3) | F80: =IF(A80="","",SUMIF('Registro de trabajos'!F:F,B80,'Registro de trabajos'!G:G)) | G80: =IF(A80="","",MAX(0,E80-F80)) | H80: =IF(A80="","",0) | I80: =IF(A80="","",0) | J80: =IF(A80="","",H80-I80) | K80: =IF(A80="","",COUNTIF('Registro de trabajos'!F:F,B80)) | L80: =IF(A80="","",F80) | M80: =IF(A80="","",IF(D80="","EN USO","FINALIZADO"))
A81: =IF('Control de rollos'!D78<>"","A","") | B81: =IF(A81="","",A81&"-"&TEXT(COUNTIF($A$2:A81,A81),"000")) | C81: =IF(A81="","",D78) | E81: =IF(A81="","",Configuración!B3) | F81: =IF(A81="","",SUMIF('Registro de trabajos'!D:D,B81,'Registro de trabajos'!E:E)) | G81: =IF(A81="","",MAX(0,E81-F81)) | H81: =IF(A81="","",SUMIF('Registro de trabajos'!D:D,B81,'Registro de trabajos'!H:H)) | I81: =IF(A81="","",Configuración!B4) | J81: =IF(A81="","",H81-I81) | K81: =IF(A81="","",COUNTIF('Registro de trabajos'!D:D,B81)) | L81: =IF(A81="","",SUMIF('Registro de trabajos'!D:D,B81,'Registro de trabajos'!G:G)) | M81: =IF(A81="","",IF(D81="","EN USO","FINALIZADO"))
A82: =IF('Control de rollos'!D80<>"","B","") | B82: =IF(A82="","",A82&"-"&TEXT(COUNTIF($A$2:A82,A82),"000")) | C82: =IF(A82="","",D80) | E82: =IF(A82="","",Configuración!B3) | F82: =IF(A82="","",SUMIF('Registro de trabajos'!F:F,B82,'Registro de trabajos'!G:G)) | G82: =IF(A82="","",MAX(0,E82-F82)) | H82: =IF(A82="","",0) | I82: =IF(A82="","",0) | J82: =IF(A82="","",H82-I82) | K82: =IF(A82="","",COUNTIF('Registro de trabajos'!F:F,B82)) | L82: =IF(A82="","",F82) | M82: =IF(A82="","",IF(D82="","EN USO","FINALIZADO"))
A83: =IF('Control de rollos'!D80<>"","A","") | B83: =IF(A83="","",A83&"-"&TEXT(COUNTIF($A$2:A83,A83),"000")) | C83: =IF(A83="","",D80) | E83: =IF(A83="","",Configuración!B3) | F83: =IF(A83="","",SUMIF('Registro de trabajos'!D:D,B83,'Registro de trabajos'!E:E)) | G83: =IF(A83="","",MAX(0,E83-F83)) | H83: =IF(A83="","",SUMIF('Registro de trabajos'!D:D,B83,'Registro de trabajos'!H:H)) | I83: =IF(A83="","",Configuración!B4) | J83: =IF(A83="","",H83-I83) | K83: =IF(A83="","",COUNTIF('Registro de trabajos'!D:D,B83)) | L83: =IF(A83="","",SUMIF('Registro de trabajos'!D:D,B83,'Registro de trabajos'!G:G)) | M83: =IF(A83="","",IF(D83="","EN USO","FINALIZADO"))
A84: =IF('Control de rollos'!D82<>"","B","") | B84: =IF(A84="","",A84&"-"&TEXT(COUNTIF($A$2:A84,A84),"000")) | C84: =IF(A84="","",D82) | E84: =IF(A84="","",Configuración!B3) | F84: =IF(A84="","",SUMIF('Registro de trabajos'!F:F,B84,'Registro de trabajos'!G:G)) | G84: =IF(A84="","",MAX(0,E84-F84)) | H84: =IF(A84="","",0) | I84: =IF(A84="","",0) | J84: =IF(A84="","",H84-I84) | K84: =IF(A84="","",COUNTIF('Registro de trabajos'!F:F,B84)) | L84: =IF(A84="","",F84) | M84: =IF(A84="","",IF(D84="","EN USO","FINALIZADO"))
A85: =IF('Control de rollos'!D82<>"","A","") | B85: =IF(A85="","",A85&"-"&TEXT(COUNTIF($A$2:A85,A85),"000")) | C85: =IF(A85="","",D82) | E85: =IF(A85="","",Configuración!B3) | F85: =IF(A85="","",SUMIF('Registro de trabajos'!D:D,B85,'Registro de trabajos'!E:E)) | G85: =IF(A85="","",MAX(0,E85-F85)) | H85: =IF(A85="","",SUMIF('Registro de trabajos'!D:D,B85,'Registro de trabajos'!H:H)) | I85: =IF(A85="","",Configuración!B4) | J85: =IF(A85="","",H85-I85) | K85: =IF(A85="","",COUNTIF('Registro de trabajos'!D:D,B85)) | L85: =IF(A85="","",SUMIF('Registro de trabajos'!D:D,B85,'Registro de trabajos'!G:G)) | M85: =IF(A85="","",IF(D85="","EN USO","FINALIZADO"))
A86: =IF('Control de rollos'!D84<>"","B","") | B86: =IF(A86="","",A86&"-"&TEXT(COUNTIF($A$2:A86,A86),"000")) | C86: =IF(A86="","",D84) | E86: =IF(A86="","",Configuración!B3) | F86: =IF(A86="","",SUMIF('Registro de trabajos'!F:F,B86,'Registro de trabajos'!G:G)) | G86: =IF(A86="","",MAX(0,E86-F86)) | H86: =IF(A86="","",0) | I86: =IF(A86="","",0) | J86: =IF(A86="","",H86-I86) | K86: =IF(A86="","",COUNTIF('Registro de trabajos'!F:F,B86)) | L86: =IF(A86="","",F86) | M86: =IF(A86="","",IF(D86="","EN USO","FINALIZADO"))
A87: =IF('Control de rollos'!D84<>"","A","") | B87: =IF(A87="","",A87&"-"&TEXT(COUNTIF($A$2:A87,A87),"000")) | C87: =IF(A87="","",D84) | E87: =IF(A87="","",Configuración!B3) | F87: =IF(A87="","",SUMIF('Registro de trabajos'!D:D,B87,'Registro de trabajos'!E:E)) | G87: =IF(A87="","",MAX(0,E87-F87)) | H87: =IF(A87="","",SUMIF('Registro de trabajos'!D:D,B87,'Registro de trabajos'!H:H)) | I87: =IF(A87="","",Configuración!B4) | J87: =IF(A87="","",H87-I87) | K87: =IF(A87="","",COUNTIF('Registro de trabajos'!D:D,B87)) | L87: =IF(A87="","",SUMIF('Registro de trabajos'!D:D,B87,'Registro de trabajos'!G:G)) | M87: =IF(A87="","",IF(D87="","EN USO","FINALIZADO"))
A88: =IF('Control de rollos'!D86<>"","B","") | B88: =IF(A88="","",A88&"-"&TEXT(COUNTIF($A$2:A88,A88),"000")) | C88: =IF(A88="","",D86) | E88: =IF(A88="","",Configuración!B3) | F88: =IF(A88="","",SUMIF('Registro de trabajos'!F:F,B88,'Registro de trabajos'!G:G)) | G88: =IF(A88="","",MAX(0,E88-F88)) | H88: =IF(A88="","",0) | I88: =IF(A88="","",0) | J88: =IF(A88="","",H88-I88) | K88: =IF(A88="","",COUNTIF('Registro de trabajos'!F:F,B88)) | L88: =IF(A88="","",F88) | M88: =IF(A88="","",IF(D88="","EN USO","FINALIZADO"))
A89: =IF('Control de rollos'!D86<>"","A","") | B89: =IF(A89="","",A89&"-"&TEXT(COUNTIF($A$2:A89,A89),"000")) | C89: =IF(A89="","",D86) | E89: =IF(A89="","",Configuración!B3) | F89: =IF(A89="","",SUMIF('Registro de trabajos'!D:D,B89,'Registro de trabajos'!E:E)) | G89: =IF(A89="","",MAX(0,E89-F89)) | H89: =IF(A89="","",SUMIF('Registro de trabajos'!D:D,B89,'Registro de trabajos'!H:H)) | I89: =IF(A89="","",Configuración!B4) | J89: =IF(A89="","",H89-I89) | K89: =IF(A89="","",COUNTIF('Registro de trabajos'!D:D,B89)) | L89: =IF(A89="","",SUMIF('Registro de trabajos'!D:D,B89,'Registro de trabajos'!G:G)) | M89: =IF(A89="","",IF(D89="","EN USO","FINALIZADO"))
A90: =IF('Control de rollos'!D88<>"","B","") | B90: =IF(A90="","",A90&"-"&TEXT(COUNTIF($A$2:A90,A90),"000")) | C90: =IF(A90="","",D88) | E90: =IF(A90="","",Configuración!B3) | F90: =IF(A90="","",SUMIF('Registro de trabajos'!F:F,B90,'Registro de trabajos'!G:G)) | G90: =IF(A90="","",MAX(0,E90-F90)) | H90: =IF(A90="","",0) | I90: =IF(A90="","",0) | J90: =IF(A90="","",H90-I90) | K90: =IF(A90="","",COUNTIF('Registro de trabajos'!F:F,B90)) | L90: =IF(A90="","",F90) | M90: =IF(A90="","",IF(D90="","EN USO","FINALIZADO"))
A91: =IF('Control de rollos'!D88<>"","A","") | B91: =IF(A91="","",A91&"-"&TEXT(COUNTIF($A$2:A91,A91),"000")) | C91: =IF(A91="","",D88) | E91: =IF(A91="","",Configuración!B3) | F91: =IF(A91="","",SUMIF('Registro de trabajos'!D:D,B91,'Registro de trabajos'!E:E)) | G91: =IF(A91="","",MAX(0,E91-F91)) | H91: =IF(A91="","",SUMIF('Registro de trabajos'!D:D,B91,'Registro de trabajos'!H:H)) | I91: =IF(A91="","",Configuración!B4) | J91: =IF(A91="","",H91-I91) | K91: =IF(A91="","",COUNTIF('Registro de trabajos'!D:D,B91)) | L91: =IF(A91="","",SUMIF('Registro de trabajos'!D:D,B91,'Registro de trabajos'!G:G)) | M91: =IF(A91="","",IF(D91="","EN USO","FINALIZADO"))
A92: =IF('Control de rollos'!D90<>"","B","") | B92: =IF(A92="","",A92&"-"&TEXT(COUNTIF($A$2:A92,A92),"000")) | C92: =IF(A92="","",D90) | E92: =IF(A92="","",Configuración!B3) | F92: =IF(A92="","",SUMIF('Registro de trabajos'!F:F,B92,'Registro de trabajos'!G:G)) | G92: =IF(A92="","",MAX(0,E92-F92)) | H92: =IF(A92="","",0) | I92: =IF(A92="","",0) | J92: =IF(A92="","",H92-I92) | K92: =IF(A92="","",COUNTIF('Registro de trabajos'!F:F,B92)) | L92: =IF(A92="","",F92) | M92: =IF(A92="","",IF(D92="","EN USO","FINALIZADO"))
A93: =IF('Control de rollos'!D90<>"","A","") | B93: =IF(A93="","",A93&"-"&TEXT(COUNTIF($A$2:A93,A93),"000")) | C93: =IF(A93="","",D90) | E93: =IF(A93="","",Configuración!B3) | F93: =IF(A93="","",SUMIF('Registro de trabajos'!D:D,B93,'Registro de trabajos'!E:E)) | G93: =IF(A93="","",MAX(0,E93-F93)) | H93: =IF(A93="","",SUMIF('Registro de trabajos'!D:D,B93,'Registro de trabajos'!H:H)) | I93: =IF(A93="","",Configuración!B4) | J93: =IF(A93="","",H93-I93) | K93: =IF(A93="","",COUNTIF('Registro de trabajos'!D:D,B93)) | L93: =IF(A93="","",SUMIF('Registro de trabajos'!D:D,B93,'Registro de trabajos'!G:G)) | M93: =IF(A93="","",IF(D93="","EN USO","FINALIZADO"))
A94: =IF('Control de rollos'!D92<>"","B","") | B94: =IF(A94="","",A94&"-"&TEXT(COUNTIF($A$2:A94,A94),"000")) | C94: =IF(A94="","",D92) | E94: =IF(A94="","",Configuración!B3) | F94: =IF(A94="","",SUMIF('Registro de trabajos'!F:F,B94,'Registro de trabajos'!G:G)) | G94: =IF(A94="","",MAX(0,E94-F94)) | H94: =IF(A94="","",0) | I94: =IF(A94="","",0) | J94: =IF(A94="","",H94-I94) | K94: =IF(A94="","",COUNTIF('Registro de trabajos'!F:F,B94)) | L94: =IF(A94="","",F94) | M94: =IF(A94="","",IF(D94="","EN USO","FINALIZADO"))
A95: =IF('Control de rollos'!D92<>"","A","") | B95: =IF(A95="","",A95&"-"&TEXT(COUNTIF($A$2:A95,A95),"000")) | C95: =IF(A95="","",D92) | E95: =IF(A95="","",Configuración!B3) | F95: =IF(A95="","",SUMIF('Registro de trabajos'!D:D,B95,'Registro de trabajos'!E:E)) | G95: =IF(A95="","",MAX(0,E95-F95)) | H95: =IF(A95="","",SUMIF('Registro de trabajos'!D:D,B95,'Registro de trabajos'!H:H)) | I95: =IF(A95="","",Configuración!B4) | J95: =IF(A95="","",H95-I95) | K95: =IF(A95="","",COUNTIF('Registro de trabajos'!D:D,B95)) | L95: =IF(A95="","",SUMIF('Registro de trabajos'!D:D,B95,'Registro de trabajos'!G:G)) | M95: =IF(A95="","",IF(D95="","EN USO","FINALIZADO"))
A96: =IF('Control de rollos'!D94<>"","B","") | B96: =IF(A96="","",A96&"-"&TEXT(COUNTIF($A$2:A96,A96),"000")) | C96: =IF(A96="","",D94) | E96: =IF(A96="","",Configuración!B3) | F96: =IF(A96="","",SUMIF('Registro de trabajos'!F:F,B96,'Registro de trabajos'!G:G)) | G96: =IF(A96="","",MAX(0,E96-F96)) | H96: =IF(A96="","",0) | I96: =IF(A96="","",0) | J96: =IF(A96="","",H96-I96) | K96: =IF(A96="","",COUNTIF('Registro de trabajos'!F:F,B96)) | L96: =IF(A96="","",F96) | M96: =IF(A96="","",IF(D96="","EN USO","FINALIZADO"))
A97: =IF('Control de rollos'!D94<>"","A","") | B97: =IF(A97="","",A97&"-"&TEXT(COUNTIF($A$2:A97,A97),"000")) | C97: =IF(A97="","",D94) | E97: =IF(A97="","",Configuración!B3) | F97: =IF(A97="","",SUMIF('Registro de trabajos'!D:D,B97,'Registro de trabajos'!E:E)) | G97: =IF(A97="","",MAX(0,E97-F97)) | H97: =IF(A97="","",SUMIF('Registro de trabajos'!D:D,B97,'Registro de trabajos'!H:H)) | I97: =IF(A97="","",Configuración!B4) | J97: =IF(A97="","",H97-I97) | K97: =IF(A97="","",COUNTIF('Registro de trabajos'!D:D,B97)) | L97: =IF(A97="","",SUMIF('Registro de trabajos'!D:D,B97,'Registro de trabajos'!G:G)) | M97: =IF(A97="","",IF(D97="","EN USO","FINALIZADO"))
A98: =IF('Control de rollos'!D96<>"","B","") | B98: =IF(A98="","",A98&"-"&TEXT(COUNTIF($A$2:A98,A98),"000")) | C98: =IF(A98="","",D96) | E98: =IF(A98="","",Configuración!B3) | F98: =IF(A98="","",SUMIF('Registro de trabajos'!F:F,B98,'Registro de trabajos'!G:G)) | G98: =IF(A98="","",MAX(0,E98-F98)) | H98: =IF(A98="","",0) | I98: =IF(A98="","",0) | J98: =IF(A98="","",H98-I98) | K98: =IF(A98="","",COUNTIF('Registro de trabajos'!F:F,B98)) | L98: =IF(A98="","",F98) | M98: =IF(A98="","",IF(D98="","EN USO","FINALIZADO"))
A99: =IF('Control de rollos'!D96<>"","A","") | B99: =IF(A99="","",A99&"-"&TEXT(COUNTIF($A$2:A99,A99),"000")) | C99: =IF(A99="","",D96) | E99: =IF(A99="","",Configuración!B3) | F99: =IF(A99="","",SUMIF('Registro de trabajos'!D:D,B99,'Registro de trabajos'!E:E)) | G99: =IF(A99="","",MAX(0,E99-F99)) | H99: =IF(A99="","",SUMIF('Registro de trabajos'!D:D,B99,'Registro de trabajos'!H:H)) | I99: =IF(A99="","",Configuración!B4) | J99: =IF(A99="","",H99-I99) | K99: =IF(A99="","",COUNTIF('Registro de trabajos'!D:D,B99)) | L99: =IF(A99="","",SUMIF('Registro de trabajos'!D:D,B99,'Registro de trabajos'!G:G)) | M99: =IF(A99="","",IF(D99="","EN USO","FINALIZADO"))
A100: =IF('Control de rollos'!D98<>"","B","") | B100: =IF(A100="","",A100&"-"&TEXT(COUNTIF($A$2:A100,A100),"000")) | C100: =IF(A100="","",D98) | E100: =IF(A100="","",Configuración!B3) | F100: =IF(A100="","",SUMIF('Registro de trabajos'!F:F,B100,'Registro de trabajos'!G:G)) | G100: =IF(A100="","",MAX(0,E100-F100)) | H100: =IF(A100="","",0) | I100: =IF(A100="","",0) | J100: =IF(A100="","",H100-I100) | K100: =IF(A100="","",COUNTIF('Registro de trabajos'!F:F,B100)) | L100: =IF(A100="","",F100) | M100: =IF(A100="","",IF(D100="","EN USO","FINALIZADO"))
...

Sheet Configuración
A1: CONFIGURACIÓN UV DTF | F1: IDs de rollo | J1: Rollo A disponible | K1: Rollo B disponible
A2: Parámetro | B2: Valor | C2: Unidad | D2: Nota | F2: A-001 | J2: =IF(AND('Control de rollos'!B2<>"",'Control de rollos'!D2=""),'Control de rollos'!B2,"") -> A-001 | K2: =IF(AND('Control de rollos'!B2<>"",'Control de rollos'!D2=""),IF(LEFT('Control de rollos'!B2,1)="B",'Control de rollos'!B2,""),"")
A3: Metros iniciales por rollo | B3: 100 | C3: m | D3: Cada rollo nuevo parte de 100 m | F3: A-002 | J3: =IF(AND('Control de rollos'!B3<>"",'Control de rollos'!D3=""),'Control de rollos'!B3,"") | K3: =IF(AND('Control de rollos'!B3<>"",'Control de rollos'!D3=""),IF(LEFT('Control de rollos'!B3,1)="B",'Control de rollos'!B3,""),"")
A4: Costo rollo A | B4: 0 | C4: S/ | D4: Ingresar costo real | F4: A-003 | J4: =IF(AND('Control de rollos'!B4<>"",'Control de rollos'!D4=""),'Control de rollos'!B4,"") -> B-002 | K4: =IF(AND('Control de rollos'!B4<>"",'Control de rollos'!D4=""),IF(LEFT('Control de rollos'!B4,1)="B",'Control de rollos'!B4,""),"") -> B-002
A5: Costo rollo B | B5: 0 | C5: S/ | D5: Ingresar costo real | F5: A-004 | J5: =IF(AND('Control de rollos'!B5<>"",'Control de rollos'!D5=""),'Control de rollos'!B5,"") | K5: =IF(AND('Control de rollos'!B5<>"",'Control de rollos'!D5=""),IF(LEFT('Control de rollos'!B5,1)="B",'Control de rollos'!B5,""),"")
A6: Fecha actual | B6: 46272 | D6: Rollo A nuevo desde esta fecha | F6: A-005 | J6: =IF(AND('Control de rollos'!B6<>"",'Control de rollos'!D6=""),'Control de rollos'!B6,"") | K6: =IF(AND('Control de rollos'!B6<>"",'Control de rollos'!D6=""),IF(LEFT('Control de rollos'!B6,1)="B",'Control de rollos'!B6,""),"")
F7: A-006 | J7: =IF(AND('Control de rollos'!B7<>"",'Control de rollos'!D7=""),'Control de rollos'!B7,"") | K7: =IF(AND('Control de rollos'!B7<>"",'Control de rollos'!D7=""),IF(LEFT('Control de rollos'!B7,1)="B",'Control de rollos'!B7,""),"")
F8: A-007 | J8: =IF(AND('Control de rollos'!B8<>"",'Control de rollos'!D8=""),'Control de rollos'!B8,"") | K8: =IF(AND('Control de rollos'!B8<>"",'Control de rollos'!D8=""),IF(LEFT('Control de rollos'!B8,1)="B",'Control de rollos'!B8,""),"")
F9: A-008 | J9: =IF(AND('Control de rollos'!B9<>"",'Control de rollos'!D9=""),'Control de rollos'!B9,"") | K9: =IF(AND('Control de rollos'!B9<>"",'Control de rollos'!D9=""),IF(LEFT('Control de rollos'!B9,1)="B",'Control de rollos'!B9,""),"")
F10: A-009 | J10: =IF(AND('Control de rollos'!B10<>"",'Control de rollos'!D10=""),'Control de rollos'!B10,"") | K10: =IF(AND('Control de rollos'!B10<>"",'Control de rollos'!D10=""),IF(LEFT('Control de rollos'!B10,1)="B",'Control de rollos'!B10,""),"")
F11: A-010 | J11: =IF(AND('Control de rollos'!B11<>"",'Control de rollos'!D11=""),'Control de rollos'!B11,"") | K11: =IF(AND('Control de rollos'!B11<>"",'Control de rollos'!D11=""),IF(LEFT('Control de rollos'!B11,1)="B",'Control de rollos'!B11,""),"")
F12: B-001 | J12: =IF(AND('Control de rollos'!B12<>"",'Control de rollos'!D12=""),'Control de rollos'!B12,"") | K12: =IF(AND('Control de rollos'!B12<>"",'Control de rollos'!D12=""),IF(LEFT('Control de rollos'!B12,1)="B",'Control de rollos'!B12,""),"")
F13: B-002 | J13: =IF(AND('Control de rollos'!B13<>"",'Control de rollos'!D13=""),'Control de rollos'!B13,"") | K13: =IF(AND('Control de rollos'!B13<>"",'Control de rollos'!D13=""),IF(LEFT('Control de rollos'!B13,1)="B",'Control de rollos'!B13,""),"")
F14: B-003 | J14: =IF(AND('Control de rollos'!B14<>"",'Control de rollos'!D14=""),'Control de rollos'!B14,"") | K14: =IF(AND('Control de rollos'!B14<>"",'Control de rollos'!D14=""),IF(LEFT('Control de rollos'!B14,1)="B",'Control de rollos'!B14,""),"")
F15: B-004 | J15: =IF(AND('Control de rollos'!B15<>"",'Control de rollos'!D15=""),'Control de rollos'!B15,"") | K15: =IF(AND('Control de rollos'!B15<>"",'Control de rollos'!D15=""),IF(LEFT('Control de rollos'!B15,1)="B",'Control de rollos'!B15,""),"")
F16: B-005 | J16: =IF(AND('Control de rollos'!B16<>"",'Control de rollos'!D16=""),'Control de rollos'!B16,"") | K16: =IF(AND('Control de rollos'!B16<>"",'Control de rollos'!D16=""),IF(LEFT('Control de rollos'!B16,1)="B",'Control de rollos'!B16,""),"")
F17: B-006 | J17: =IF(AND('Control de rollos'!B17<>"",'Control de rollos'!D17=""),'Control de rollos'!B17,"") | K17: =IF(AND('Control de rollos'!B17<>"",'Control de rollos'!D17=""),IF(LEFT('Control de rollos'!B17,1)="B",'Control de rollos'!B17,""),"")
F18: B-007 | J18: =IF(AND('Control de rollos'!B18<>"",'Control de rollos'!D18=""),'Control de rollos'!B18,"") | K18: =IF(AND('Control de rollos'!B18<>"",'Control de rollos'!D18=""),IF(LEFT('Control de rollos'!B18,1)="B",'Control de rollos'!B18,""),"")
... F21: B-010 | J21: =IF(AND('Control de rollos'!B21<>"",'Control de rollos'!D21=""),'Control de rollos'!B21,"") | K21: =IF(AND('Control de rollos'!B21<>"",'Control de rollos'!D21=""),IF(LEFT('Control de rollos'!B21,1)="B",'Control de rollos'!B21,""),"")
J22: =IF(AND('Control de rollos'!B22<>"",'Control de rollos'!D22=""),'Control de rollos'!B22,"") | K22: =IF(AND('Control de rollos'!B22<>"",'Control de rollos'!D22=""),IF(LEFT('Control de rollos'!B22,1)="B",'Control de rollos'!B22,""),"")
J23: =IF(AND('Control de rollos'!B23<>"",'Control de rollos'!D23=""),'Control de rollos'!B23,"") | K23: =IF(AND('Control de rollos'!B23<>"",'Control de rollos'!D23=""),IF(LEFT('Control de rollos'!B23,1)="B",'Control de rollos'!B23,""),"")
J24: =IF(AND('Control de rollos'!B24<>"",'Control de rollos'!D24=""),'Control de rollos'!B24,"") | K24: =IF(AND('Control de rollos'!B24<>"",'Control de rollos'!D24=""),IF(LEFT('Control de rollos'!B24,1)="B",'Control de rollos'!B24,""),"")
J25: =IF(AND('Control de rollos'!B25<>"",'Control de rollos'!D25=""),'Control de rollos'!B25,"") | K25: =IF(AND('Control de rollos'!B25<>"",'Control de rollos'!D25=""),IF(LEFT('Control de rollos'!B25,1)="B",'Control de rollos'!B25,""),"")
J26: =IF(AND('Control de rollos'!B26<>"",'Control de rollos'!D26=""),'Control de rollos'!B26,"") | K26: =IF(AND('Control de rollos'!B26<>"",'Control de rollos'!D26=""),IF(LEFT('Control de rollos'!B26,1)="B",'Control de rollos'!B26,""),"")
J27: =IF(AND('Control de rollos'!B27<>"",'Control de rollos'!D27=""),'Control de rollos'!B27,"") | K27: =IF(AND('Control de rollos'!B27<>"",'Control de rollos'!D27=""),IF(LEFT('Control de rollos'!B27,1)="B",'Control de rollos'!B27,""),"")
J28: =IF(AND('Control de rollos'!B28<>"",'Control de rollos'!D28=""),'Control de rollos'!B28,"") | K28: =IF(AND('Control de rollos'!B28<>"",'Control de rollos'!D28=""),IF(LEFT('Control de rollos'!B28,1)="B",'Control de rollos'!B28,""),"")
J29: =IF(AND('Control de rollos'!B29<>"",'Control de rollos'!D29=""),'Control de rollos'!B29,"") | K29: =IF(AND('Control de rollos'!B29<>"",'Control de rollos'!D29=""),IF(LEFT('Control de rollos'!B29,1)="B",'Control de rollos'!B29,""),"")
J30: =IF(AND('Control de rollos'!B30<>"",'Control de rollos'!D30=""),'Control de rollos'!B30,"") | K30: =IF(AND('Control de rollos'!B30<>"",'Control de rollos'!D30=""),IF(LEFT('Control de rollos'!B30,1)="B",'Control de rollos'!B30,""),"")
J31: =IF(AND('Control de rollos'!B31<>"",'Control de rollos'!D31=""),'Control de rollos'!B31,"") | K31: =IF(AND('Control de rollos'!B31<>"",'Control de rollos'!D31=""),IF(LEFT('Control de rollos'!B31,1)="B",'Control de rollos'!B31,""),"")
J32: =IF(AND('Control de rollos'!B32<>"",'Control de rollos'!D32=""),'Control de rollos'!B32,"") | K32: =IF(AND('Control de rollos'!B32<>"",'Control de rollos'!D32=""),IF(LEFT('Control de rollos'!B32,1)="B",'Control de rollos'!B32,""),"")
J33: =IF(AND('Control de rollos'!B33<>"",'Control de rollos'!D33=""),'Control de rollos'!B33,"") | K33: =IF(AND('Control de rollos'!B33<>"",'Control de rollos'!D33=""),IF(LEFT('Control de rollos'!B33,1)="B",'Control de rollos'!B33,""),"")
... J101: =IF(AND('Control de rollos'!B101<>"",'Control de rollos'!D101=""),'Control de rollos'!B101,"") | K101: =IF(AND('Control de rollos'!B101<>"",'Control de rollos'!D101=""),IF(LEFT('Control de rollos'!B101,1)="B",'Control de rollos'!B101,""),"")
